Workbook

Sheet FAME Persistence2
A1: 53 | B1: MonthlyData
A2: MonthlyFAME | B2: $A$7 | C2: A1:A780 | D2: 21946 | E2: 45471.465 | F2: TRUE | G2: FAMEDATE | H2: 1960 | I2: 2024 | J2: 0 | K2: m | L2: FALSE | M2: FALSE | N2: FALSE
A3: MonthlyFAME | B3: $B$7 | C3: A1:A780 | E3: 45471.465 | F3: TRUE | G3: ecy2.m | H3: 1960 | I3: 2024 | J3: 0 | K3: m | L3: FALSE | M3: FALSE | N3: FALSE
A4: MonthlyFAME | B4: $C$7 | C4: A1:A780 | E4: 45471.465 | F4: TRUE | G4: totexq1.m | H4: 1960 | I4: 2024 | J4: 0 | K4: m | L4: FALSE | M4: FALSE | N4: FALSE
A5: MonthlyFAME | B5: $D$7 | C5: A1:A780 | E5: 45471.465 | F5: TRUE | G5: totreq1.m | H5: 1960 | I5: 2024 | J5: 0 | K5: m | L5: FALSE | M5: FALSE | N5: FALSE
A6: MonthlyFAME | B6: $E$7 | C6: A1:A780 | E6: 45471.465 | F6: TRUE | G6: cbiout.m | H6: 1960 | I6: 2024 | J6: 0 | K6: m | L6: FALSE | M6: FALSE | N6: FALSE
A7: MonthlyFAME | B7: $F$7 | C7: A1:A780 | E7: 45471.465 | F7: TRUE | G7: cipsmba.m | H7: 1960 | I7: 2024 | J7: 0 | K7: m | L7: FALSE | M7: FALSE | N7: FALSE
A8: MonthlyFAME | B8: $G$7 | C8: A1:A780 | E8: 45471.465 | F8: TRUE | G8: CIPSSBA.m | H8: 1960 | I8: 2024 | J8: 0 | K8: m | L8: FALSE | M8: FALSE | N8: FALSE
A9: MonthlyFAME | B9: $H$7 | C9: A1:A780 | E9: 45471.465 | F9: TRUE | G9: CIPSCBA.m | H9: 1960 | I9: 2024 | J9: 0 | K9: m | L9: FALSE | M9: FALSE | N9: FALSE
A10: MonthlyFAME | B10: $I$7 | C10: A1:A780 | E10: 45471.465 | F10: TRUE | G10: gfkecbalsa.m | H10: 1960 | I10: 2024 | J10: 0 | K10: m | L10: FALSE | M10: FALSE | N10: FALSE
A11: MonthlyFAME | B11: $J$7 | C11: A1:A780 | D11: 41.3 | E11: 45471.465 | F11: TRUE | G11: k222.m | H11: 1960 | I11: 2024 | J11: 0 | K11: m | L11: FALSE | M11: FALSE | N11: FALSE
A12: MonthlyFAME | B12: $K$7 | C12: A1:A780 | E12: 45471.465 | F12: TRUE | G12: ecyc_dp.m | H12: 1960 | I12: 2024 | J12: 0 | K12: m | L12: FALSE | M12: FALSE | N12: FALSE
A13: MonthlyFAME | B13: $L$7 | D13: #N/A | E13: 0 | F13: TRUE | G13: x12(TOTCARS.M,mult,$A$2,L) | H13: 1960 | I13: 2024 | J13: 0 | K13: m | L13: FALSE | M13: FALSE | N13: FALSE
A14: MonthlyFAME | B14: $M$7 | C14: A1:A780 | E14: 45471.465 | F14: TRUE | G14: bqkq.m | H14: 1960 | I14: 2024 | J14: 0 | K14: m | L14: FALSE | M14: FALSE | N14: FALSE
A15: MonthlyFAME | B15: $N$7 | C15: A1:A780 | E15: 45471.465 | F15: TRUE | G15: bqko.m | H15: 1960 | I15: 2024 | J15: 0 | K15: m | L15: FALSE | M15: FALSE | N15: FALSE
A16: MonthlyFAME | B16: $O$7 | C16: A1:A780 | E16: 45471.465 | F16: TRUE | G16: 100*mgsc.m[t-1]/(mgrz.m[t-1]+mgsc.m[t-1]) | H16: 1960 | I16: 2024 | J16: 0 | K16: m | L16: FALSE | M16: FALSE | N16: FALSE
A17: MonthlyFAME | B17: $P$7 | C17: A1:A780 | E17: 45471.465 | F17: TRUE | G17: mgrz.m[t-1] | H17: 1960 | I17: 2024 | J17: 0 | K17: m | L17: FALSE | M17: FALSE | N17: FALSE
A18: MonthlyFAME | B18: $Q$7 | C18: A1:A780 | E18: 45471.465 | F18: TRUE | G18: ybus.m[t-1] | H18: 1960 | I18: 2024 | J18: 0 | K18: m | L18: FALSE | M18: FALSE | N18: FALSE
A19: MonthlyFAME | B19: $R$7 | C19: A1:A780 | E19: 45471.465 | F19: TRUE | G19: ap2y.m[t-1] | H19: 1960 | I19: 2024 | J19: 0 | K19: m | L19: FALSE | M19: FALSE | N19: FALSE
A20: MonthlyFAME | B20: $S$7 | C20: A1:A780 | E20: 45471.465 | F20: TRUE | G20: overlay(kab9_hist.m,kab9_dp.m) | H20: 1960 | I20: 2024 | J20: 0 | K20: m | L20: FALSE | M20: FALSE | N20: FALSE
A21: MonthlyFAME | B21: $T$7 | C21: A1:A780 | E21: 45471.465 | F21: TRUE | G21: bcjd.m | H21: 1960 | I21: 2024 | J21: 0 | K21: m | L21: FALSE | M21: FALSE | N21: FALSE
A22: MonthlyFAME | B22: $U$7 | D22: #N/A | E22: 0 | F22: TRUE | G22: x12(d7bt3dpm.m,mult,$A$2,L) | H22: 1960 | I22: 2024 | J22: 0 | K22: m | L22: FALSE | M22: FALSE | N22: FALSE
A23: MonthlyFAME | B23: $V$7 | D23: #N/A | E23: 0 | F23: TRUE | G23: x12(d7bt3dpm.m,mult,$A$2,L) | H23: 1960 | I23: 2024 | J23: 0 | K23: m | L23: FALSE | M23: FALSE | N23: FALSE
A24: MonthlyFAME | B24: $W$7 | D24: #N/A | E24: 0 | F24: TRUE | G24: x12(chaw.m,mult,$A$2,L) | H24: 1960 | I24: 2024 | J24: 0 | K24: m | L24: FALSE | M24: FALSE | N24: FALSE
A25: MonthlyFAME | B25: $X$7 | D25: #N/A | E25: 0 | F25: TRUE | G25: x12(chmk.m,mult,$A$2,L) | H25: 1960 | I25: 2024 | J25: 0 | K25: m | L25: FALSE | M25: FALSE | N25: FALSE
A26: MonthlyFAME | B26: $Y$7 | D26: #N/A | E26: 0 | F26: TRUE | G26: x12(gb7s.m,mult,$A$2,L) | H26: 1960 | I26: 2024 | J26: 0 | K26: m | L26: FALSE | M26: FALSE | N26: FALSE
A27: MonthlyFAME | B27: $Z$7 | D27: #N/A | E27: 0 | F27: TRUE | G27: x12(ghip.m,mult,$A$2,L) | H27: 1960 | I27: 2024 | J27: 0 | K27: m | L27: FALSE | M27: FALSE | N27: FALSE
A28: MonthlyFAME | B28: $AA$7 | D28: #N/A | E28: 0 | F28: TRUE | G28: x12(NWHPISA.M,mult,$A$2,L) | H28: 1960 | I28: 2024 | J28: 0 | K28: m | L28: FALSE | M28: FALSE | N28: FALSE
A29: MonthlyFAME | B29: $AB$7 | C29: A1:A780 | E29: 45471.466 | F29: TRUE | G29: conv2ma(oilbrnp_p.B) | H29: 1960 | I29: 2024 | J29: 0 | K29: m | L29: FALSE | M29: FALSE | N29: FALSE
A30: MonthlyFAME | B30: $AC$7 | C30: A1:A780 | E30: 45471.466 | F30: TRUE | G30: M4SA.M | H30: 1960 | I30: 2024 | J30: 0 | K30: m | L30: FALSE | M30: FALSE | N30: FALSE
A31: MonthlyFAME | B31: $AD$7 | C31: A1:A780 | E31: 45471.466 | F31: TRUE | G31: vtvx.m | H31: 1960 | I31: 2024 | J31: 0 | K31: m | L31: FALSE | M31: FALSE | N31: FALSE
A32: MonthlyFAME | B32: $AE$7 | C32: A1:A780 | E32: 45471.466 | F32: TRUE | G32: conv2ma(ukbrbase.b) | H32: 1960 | I32: 2024 | J32: 0 | K32: m | L32: FALSE | M32: FALSE | N32: FALSE
A33: MonthlyFAME | B33: $AF$7 | C33: A1:A780 | E33: 45471.466 | F33: TRUE | G33: conv2ma(BP0003M.B) | H33: 1960 | I33: 2024 | J33: 0 | K33: m | L33: FALSE | M33: FALSE | N33: FALSE
A34: MonthlyFAME | B34: $AG$7 | C34: A1:A780 | E34: 45471.466 | F34: TRUE | G34: conv2ma(seri.b) | H34: 1960 | I34: 2024 | J34: 0 | K34: m | L34: FALSE | M34: FALSE | N34: FALSE
A35: MonthlyFAME | B35: $AH$7 | C35: A1:A780 | E35: 45471.466 | F35: TRUE | G35: conv2ma(asx.b) | H35: 1960 | I35: 2024 | J35: 0 | K35: m | L35: FALSE | M35: FALSE | N35: FALSE
A36: MonthlyFAME | B36: $AI$7 | C36: A1:A780 | E36: 45471.466 | F36: TRUE | G36: conv2ma(mcx.b) | H36: 1960 | I36: 2024 | J36: 0 | K36: m | L36: FALSE | M36: FALSE | N36: FALSE
A37: MonthlyFAME | B37: $AJ$7 | C37: A1:A780 | E37: 45471.466 | F37: TRUE | G37: conv2ma(ukfoceq.b) | H37: 1960 | I37: 2024 | J37: 0 | K37: m | L37: FALSE | M37: FALSE | N37: FALSE
A38: MonthlyFAME | B38: $AK$7 | C38: A1:A780 | E38: 45471.466 | F38: TRUE | G38: conv2ma(spx.b) | H38: 1960 | I38: 2024 | J38: 0 | K38: m | L38: FALSE | M38: FALSE | N38: FALSE
A39: MonthlyFAME | B39: $AL$7 | C39: A1:A780 | E39: 45471.466 | F39: TRUE | G39: conv2ma(djeurst_pi.B) | H39: 1960 | I39: 2024 | J39: 0 | K39: m | L39: FALSE | M39: FALSE | N39: FALSE
A40: MonthlyFAME | B40: $AM$7 | C40: A1:A780 | E40: 45471.466 | F40: TRUE | G40: conv2ma(vix.b) | H40: 1960 | I40: 2024 | J40: 0 | K40: m | L40: FALSE | M40: FALSE | N40: FALSE
... A45: MonthlyFAME | B45: $AR$7 | C45: A1:A780 | E45: 45471.466 | F45: TRUE | G45: VISA_SA.m | H45: 1960 | I45: 2024 | J45: 0 | K45: m | L45: FALSE | M45: FALSE | N45: FALSE
A46: MonthlyFAME | B46: $AY$8 | D46: #N/A | E46: 0 | F46: TRUE | H46: 1960 | I46: 2024 | J46: 0 | K46: m | L46: FALSE | M46: FALSE | N46: FALSE
A47: MonthlyFAME | B47: $AZ$8 | D47: #N/A | E47: 0 | F47: TRUE | H47: 1960 | I47: 2024 | J47: 0 | K47: m | L47: FALSE | M47: FALSE | N47: FALSE
A48: QuarterlyFAME | B48: $A$6 | C48: A1:A256 | D48: 22006 | E48: 45161.482 | F48: TRUE | G48: FAMEDATE | H48: 1960 | I48: 2023 | J48: 0 | K48: q | L48: FALSE | M48: FALSE | N48: FALSE
A49: QuarterlyFAME | B49: $B$6 | C49: A1:A256 | D49: 151420 | E49: 45161.482 | F49: TRUE | G49: abmi.q | H49: 1960 | I49: 2023 | J49: 0 | K49: q | L49: FALSE | M49: FALSE | N49: FALSE
A50: QuarterlyFAME | B50: $C$6 | C50: A1:A256 | D50: 77407 | E50: 45161.482 | F50: TRUE | G50: ons.uk.hhd.abjr.q | H50: 1960 | I50: 2023 | J50: 0 | K50: q | L50: FALSE | M50: FALSE | N50: FALSE
A51: QuarterlyFAME | B51: $D$6 | C51: A1:A256 | D51: 22788 | E51: 45161.482 | F51: TRUE | G51: ons.uk.ado.npqt.q | H51: 1960 | I51: 2023 | J51: 0 | K51: q | L51: FALSE | M51: FALSE | N51: FALSE
A52: QuarterlyFAME | B52: $E$6 | C52: A1:A256 | E52: 45161.482 | F52: TRUE | G52: ybus.q*13 | H52: 1960 | I52: 2023 | J52: 0 | K52: q | L52: FALSE | M52: FALSE | N52: FALSE
A53: QuarterlyFAME | B53: $G$6 | C53: A1:A256 | E53: 45161.49 | F53: TRUE | G53: a23_ckp_fin.q | H53: 1960 | I53: 2023 | J53: 0 | K53: q | L53: FALSE | M53: FALSE | N53: FALSE
A54: QuarterlyFAME | B54: $F$6 | C54: A1:A256 | E54: 45161.49 | F54: TRUE | G54: a23_outputgap_fin.q | H54: 1960 | I54: 2023 | J54: 0 | K54: q | L54: FALSE | M54: FALSE | N54: FALSE

Sheet MonthlyFAME
C1: Production, Services and Trade | H1: Labour market | N1: Prices
A2: 1960 | C2: UK INDEX OF PRODUCTION - ALL PRODUCTION INDUSTRIES VOLA | D2: UK INDEX OF SERVICES - TOTAL VOLA | E2: New Cars Registrations | F2: UK ITS EXPORTS F.O.B. TOTAL CURA | G2: UK ITS IMPORTS C.I.F. TOTAL CURA | H2: UK LFS: UNEMPLOYMENT RATE, ALL, AGED 16 & OVER SADJ | I2: UK LFS: IN EMPLOYMENT, ALL, AGED 16-64 VOLA | J2: HOURS WORKED | K2: UK JOB VACANCIES (STANDARDIZED) VOLA | L2: Average Weekly Earnings | M2: Claimant Count Rate | N2: CPI all items | O2: Core CPI | P2: RPI all items | Q2: RPI ex Mortgages Interest Payments (RPIX) | R2: PPI Output | S2: PPI Input | T2: Nationwide House Price MoM | U2: Oil Brent | AA2: UK BOE AGENTS SCORES: TURNOVER - CONSUMER SERVICES NADJ | AB2: UK GDP: GROSS VALUE ADDED (BASIC PRICES) VOLA | AC2: Unemployment Rate (Ry’s long run series) | AD2: Vacancies (Ry’s Long Run Series) | AE2: Index of Production (Ry’s LR series (not sure if it’s needed)
A3: 2024 | B3: 1 | C3: 9 | D3: 10 | E3: 11 | F3: 12 | G3: 13 | H3: 14 | I3: 15 | J3: 16 | K3: 17 | L3: 18 | M3: 19 | N3: 20 | O3: 21 | P3: 22 | Q3: 23 | R3: 24 | S3: 25 | T3: 26 | U3: 27
B4: SA | C4: SA | D4: SA | E4: SA | F4: SA | G4: SA | H4: SA | I4: SA | K4: SA | L4: SA | M4: x12 | N4: x12 | O4: x12 | P4: x12 | Q4: x12 | R4: x12 | S4: x12
A5: m | B5: GDP_M | C5: IoP | D5: IoS | F5: Exports | G5: Imports | H5: UR | I5: EMP | J5: Hours | K5: Vacancies | N5: CPI | AA5: BOEAS_CS | AB5: GVA | AC5: =[1]RawData!AD3 -> UR_RY | AD5: =[1]RawData!AE3 -> Vacancies_RY | AE5: IoP_RY
B6: ecy2.m | C6: k222.m | D6: ecyc_dp.m | E6: x12(TOTCARS.M,mult,$A$2,L) | F6: bqkq.m | G6: bqko.m | H6: 100*mgsc.m[t-1]/(mgrz.m[t-1]+mgsc.m[t-1]) | I6: mgrz.m[t-1] | J6: ybus.m[t-1] | K6: ap2y.m[t-1] | L6: overlay(kab9_hist.m,kab9_dp.m) | M6: bcjd.m | N6: x12(d7bt3dpm.m,mult,$A$2,L) | O6: x12(d7bt3dpm.m,mult,$A$2,L) | P6: x12(chaw.m,mult,$A$2,L) | Q6: x12(chmk.m,mult,$A$2,L) | R6: x12(gb7s.m,mult,$A$2,L) | S6: x12(ghip.m,mult,$A$2,L) | T6: x12(NWHPISA.M,mult,$A$2,L) | U6: conv2ma(oilbrnp_p.B)
A7: =[2]!FAMEData("FAMEDATE",A2,A3, 0,A5, "Down", "No Heading", "Normal") -> #NAME? | B7: =[2]!FAMEData(B6, $A$2, $A$3, 0,$A$5,"Down","No Heading","Normal") -> #NAME? | C7: =[2]!FAMEData(C6, $A$2, $A$3, 0,$A$5,"Down","No Heading","Normal") -> #NAME? | D7: =[2]!FAMEData(D6, $A$2, $A$3, 0,$A$5,"Down","No Heading","Normal") -> #NAME? | E7: =[2]!FAMEData(E6, $A$2, $A$3, 0,$A$5,"Down","No Heading","Normal") -> #NAME? | F7: =[2]!FAMEData(F6, $A$2, $A$3, 0,$A$5,"Down","No Heading","Normal") -> #NAME? | G7: =[2]!FAMEData(G6, $A$2, $A$3, 0,$A$5,"Down","No Heading","Normal") -> #NAME? | H7: =[2]!FAMEData(H6, $A$2, $A$3, 0,$A$5,"Down","No Heading","Normal") -> #NAME? | I7: =[2]!FAMEData(I6, $A$2, $A$3, 0,$A$5,"Down","No Heading","Normal") -> #NAME? | ... U7: =[2]!FAMEData(U6, $A$2, $A$3, 0,$A$5,"Down","No Heading","Normal") -> #NAME?
A8: 21975 | C8: 41.3 | AB8: =[2]!FAMEData(AB7, $A$2, $A$3, 0,$A$5,"Down","No Heading","Normal") -> #NAME? | AC8: =[2]!FAMEData(AC7, $A$2, $A$3, 0,$A$5,"Down","No Heading","Normal") -> #NAME?
A9: 22006 | C9: 41.3
A10: 22036 | C10: 41.3
A11: 22067 | C11: 41.3
A12: 22097 | C12: 41.3
A13: 22128 | C13: 41.3
A14: 22159 | C14: 41.4
A15: 22189 | C15: 41.7
A16: 22220 | C16: 41.9
A17: 22250 | C17: 41.9
A18: 22281 | C18: 41.7
A19: 22312 | C19: 41.3
A20: 22340 | C20: 41.1
... A42: 23011 | C42: 41.7
A43: 23042 | C43: 41.4 | L43: 10.557267
A44: 23070 | C44: 41.4 | L44: 10.62593
A45: 23101 | C45: 41.8 | L45: 10.48111
A46: 23131 | C46: 42.3 | L46: 10.492773
A47: 23162 | C47: 42.9 | L47: 10.585569
A48: 23192 | C48: 43.5 | L48: 10.774261
A49: 23223 | C49: 43.9 | L49: 10.841342
A50: 23254 | C50: 44.2 | L50: 11.065232
A51: 23284 | C51: 44.4 | L51: 10.773488
A52: 23315 | C52: 44.6 | L52: 10.753324
A53: 23345 | C53: 45 | L53: 11.004215
A54: 23376 | C54: 45.5 | L54: 11.431966
... A138: 25933 | C138: 55.5 | L138: 19.289937
A139: 25964 | C139: 55.8 | L139: 19.667394 | M139: 533.6
A140: 25992 | C140: 54.7 | L140: 19.759731 | M140: 552.3
A141: 26023 | C141: 54 | H141: 3.829172 | I141: 24613 | J141: 864.3 | L141: 19.821442 | M141: 573.5
A142: 26053 | C142: 54.8 | H142: 3.9025535 | I142: 24575 | J142: 862.7 | L142: 19.846515 | M142: 599.1
A143: 26084 | C143: 55.1 | H143: 3.9989055 | I143: 24559 | J143: 862.5 | L143: 20.211309 | M143: 641.7
A144: 26114 | C144: 54.9 | H144: 4.0818718 | I144: 24556 | J144: 862.8 | L144: 20.37123 | M144: 655.2
A145: 26145 | C145: 54.7 | H145: 4.1479514 | I145: 24541 | J145: 862.6 | L145: 20.266637 | M145: 662.9
A146: 26176 | C146: 55 | H146: 4.1757898 | I146: 24508 | J146: 862.3 | L146: 20.568736 | M146: 664.1
A147: 26206 | C147: 54.5 | H147: 4.2129992 | I147: 24464 | J147: 861.3 | L147: 20.654111 | M147: 684
A148: 26237 | C148: 54.6 | H148: 4.2721643 | I148: 24424 | J148: 860.8 | L148: 20.937856 | M148: 715.8
A149: 26267 | C149: 54.5 | H149: 4.3628239 | I149: 24398 | J149: 860.8 | L149: 20.910337 | M149: 747.6
A150: 26298 | C150: 54.8 | H150: 4.4382639 | I150: 24395 | J150: 861.7 | L150: 21.000458 | M150: 757.7
A151: 26329 | C151: 53.3 | H151: 4.4720059 | I151: 24416 | J151: 863.5 | L151: 21.399954 | M151: 754.1
A152: 26358 | C152: 49 | H152: 4.4875801 | I152: 24455 | J152: 866.1 | L152: 21.478133 | M152: 768.5
... A246: 29220 | C246: 66 | H246: 5.4988599 | I246: 25280 | J246: 879.8 | L246: 74.647602 | M246: 1044.1
A247: 29251 | C247: 65.5 | F247: 6777 | G247: 6619 | H247: 5.565932 | I247: 25280 | J247: 878.7 | L247: 75.422489 | M247: 1060.8
A248: 29280 | C248: 64 | F248: 6552 | G248: 6734 | H248: 5.6772797 | I248: 25270 | J248: 877.1 | L248: 77.044638 | M248: 1096
A249: 29311 | C249: 63.6 | F249: 6072 | G249: 6182 | H249: 5.811698 | I249: 25250 | J249: 875.1 | L249: 78.863103 | M249: 1125.1
A250: 29341 | C250: 61.8 | F250: 6148 | G250: 6518 | H250: 5.9728743 | I250: 25235 | J250: 873.1 | L250: 79.906981 | M250: 1172.3
A251: 29372 | C251: 61.9 | F251: 6192 | G251: 6002 | H251: 6.1348323 | I251: 25215 | J251: 870.7 | L251: 81.031558 | M251: 1211.1
A252: 29402 | C252: 62 | F252: 6128 | G252: 6034 | H252: 6.3220528 | I252: 25190 | J252: 868.2 | L252: 82.481814 | M252: 1261.9
A253: 29433 | C253: 60.7 | F253: 6188 | G253: 5695 | H253: 6.5240006 | I253: 25160 | J253: 865.3 | L253: 82.866394 | M253: 1324.8
A254: 29464 | C254: 59.7 | F254: 5806 | G254: 5697 | H254: 6.7859529 | I254: 25110 | J254: 861.6 | L254: 84.945097 | M254: 1421.5
A255: 29494 | C255: 58.6 | F255: 5899 | G255: 5384 | H255: 7.0673344 | I255: 25050 | J255: 857.4 | L255: 87.723323 | M255: 1491.6
A256: 29525 | C256: 58.5 | F256: 5976 | G256: 5291 | H256: 7.3737673 | I256: 24985 | J256: 853.2 | L256: 86.267373 | M256: 1579.6
A257: 29555 | C257: 58.5 | F257: 5995 | G257: 5334 | H257: 7.6948726 | I257: 24915 | J257: 848.7 | L257: 87.092534 | M257: 1689.8
A258: 29586 | C258: 58.1 | F258: 6012 | G258: 5655 | H258: 8.0261989 | I258: 24855 | J258: 844.6 | L258: 89.143632 | M258: 1777.4
... A335: 31928 | C335: 70.2 | F335: 7720 | G335: 8641 | H335: 10.896341 | I335: 25031 | J335: 840.5 | L335: 150.08548 | M335: 2845.7
A336: 31958 | C336: 69.9 | F336: 7936 | G336: 8593 | H336: 10.739042 | I336: 25110 | J336: 843.3 | L336: 150.75884 | M336: 2807.7 | U336: 18.856818
A337: 31989 | C337: 71.2 | F337: 8100 | G337: 8961 | H337: 10.556404 | I337: 25190 | J337: 846.3 | L337: 152.02354 | M337: 2764 | U337: 19.856522
A338: 32020 | C338: 71 | F338: 8222 | G338: 9001 | H338: 10.386893 | I338: 25270 | J338: 849.5 | L338: 153.09723 | M338: 2721 | U338: 18.979524
A339: 32050 | C339: 70.5 | F339: 8154 | G339: 8872 | H339: 10.219625 | I339: 25345 | J339: 852.3 | L339: 153.53115 | M339: 2677.6 | U339: 18.313182
A340: 32081 | C340: 71.4 | F340: 8171 | G340: 8837 | H340: 10.043174 | I340: 25420 | J340: 855 | L340: 155.07082 | M340: 2621 | U340: 18.757727
A341: 32111 | C341: 71.3 | F341: 8246 | G341: 9093 | H341: 9.8575116 | I341: 25495 | J341: 857.9 | L341: 156.31487 | M341: 2565.6 | U341: 17.780952
A342: 32142 | C342: 71.9 | F342: 8101 | G342: 9305 | H342: 9.6800396 | I342: 25575 | J342: 860.8 | L342: 157.41937 | M342: 2535.8 | U342: 17.056087
A343: 32173 | C343: 72.6 | F343: 7900 | G343: 8925 | H343: 9.5125564 | I343: 25655 | J343: 863.9 | L343: 158.46891 | M343: 2488.6 | U343: 16.830476
A344: 32202 | C344: 71.7 | F344: 8157 | G344: 9329 | H344: 9.3599183 | I344: 25730 | J344: 866.9 | L344: 158.85975 | M344: 2449.4 | U344: 15.665714
A345: 32233 | C345: 72.9 | F345: 8102 | G345: 9146 | H345: 9.1981132 | I345: 25795 | J345: 869.4 | L345: 160.99015 | M345: 2405.6 | U345: 14.728261
A346: 32263 | C346: 72.3 | F346: 8401 | G346: 9445 | H346: 9.0365472 | I346: 25860 | J346: 871.9 | L346: 161.1917 | M346: 2362.4 | U346: 16.511905
A347: 32294 | C347: 73.1 | F347: 8126 | G347: 9583 | H347: 8.8821689 | I347: 25913 | J347: 874 | L347: 162.80181 | M347: 2317.2 | U347: 16.288636
... A450: 35430 | C450: 81.8 | F450: 12970 | G450: 13792 | H450: 7.8411369 | I450: 26198 | J450: 866.1 | L450: 267.10557 | M450: 1872.1 | U450: 23.823182
A451: 35461 | B451: 63.3 | C451: 81.8 | D451: 58.9698 | F451: 19558 | G451: 17288 | H451: 7.669046 | I451: 26258 | J451: 867.8 | L451: 267.57221 | M451: 1818.4 | U451: 23.472609
A452: 35489 | B452: 64 | C452: 82.1 | D452: 59.7182 | F452: 19053 | G452: 17107 | H452: 7.4890177 | I452: 26324 | J452: 870.2 | L452: 267.76415 | M452: 1752.8 | U452: 20.827
A453: 35520 | B453: 64 | C453: 80.9 | D453: 59.97 | F453: 18509 | G453: 17733 | H453: 7.3245275 | I453: 26381 | J453: 873.7 | L453: 271.21285 | M453: 1704.3 | U453: 19.055238
A454: 35550 | B454: 64.6 | C454: 82.9 | D454: 60.1678 | F454: 19942 | G454: 18571 | H454: 7.2050562 | I454: 26428 | J454: 877.5 | L454: 269.59258 | M454: 1662.6 | U454: 17.481818
A455: 35581 | B455: 64.1 | C455: 82.6 | D455: 59.5863 | F455: 19180 | G455: 17946 | H455: 7.1832123 | I455: 26450 | J455: 878.1 | L455: 270.53525 | M455: 1619.6 | U455: 19.127273
A456: 35611 | B456: 64.5 | C456: 82.8 | D456: 59.9621 | F456: 18731 | G456: 18573 | H456: 7.1801155 | I456: 26514 | J456: 878.3 | L456: 270.91307 | M456: 1571.5 | U456: 17.589524
A457: 35642 | B457: 64.8 | C457: 84.5 | D457: 60.0228 | F457: 19197 | G457: 18464 | H457: 7.2893337 | I457: 26493 | J457: 877 | L457: 272.78631 | M457: 1554.1 | U457: 18.503913
A458: 35673 | B458: 64.9 | C458: 83.5 | D458: 60.3402 | F458: 18364 | G458: 17051 | H458: 7.0870281 | I458: 26509 | J458: 877.9 | L458: 274.44992 | M458: 1526.5 | U458: 18.639048
A459: 35703 | B459: 65 | C459: 84 | D459: 60.3826 | F459: 19128 | G459: 17769 | H459: 6.840094 | I459: 26572 | J459: 880.2 | L459: 275.77948 | M459: 1497.8 | U459: 18.476818
A460: 35734 | B460: 65.4 | C460: 85 | D460: 60.6386 | F460: 19429 | G460: 18478 | H460: 6.6954265 | I460: 26603 | J460: 882.9 | L460: 276.63451 | M460: 1464.1 | U460: 19.906957
A461: 35764 | B461: 65.7 | C461: 85.1 | D461: 60.8828 | F461: 18977 | G461: 18202 | H461: 6.6189624 | I461: 26622 | J461: 884.5 | L461: 278.17034 | M461: 1431.7 | U461: 19.1495
A462: 35795 | B462: 66.2 | C462: 85.3 | D462: 61.4453 | F462: 20445 | G462: 18889 | H462: 6.5403509 | I462: 26636 | J462: 879.8 | L462: 279.89423 | M462: 1410.5 | U462: 17.094348
... A503: 37042 | B503: 73.8 | C503: 96.8 | D503: 68.1267 | F503: 22132 | G503: 24425 | H503: 4.9124614 | I503: 27699 | J503: 906.5 | L503: 326.62827 | M503: 974.9 | U503: 28.39913
A504: 37072 | B504: 74.1 | C504: 97.5 | D504: 68.3656 | F504: 22577 | G504: 25351 | H504: 5.0317052 | I504: 27707 | J504: 906.4 | K504: 680 | L504: 328.44501 | M504: 961.6 | U504: 27.771905
A505: 37103 | B505: 74.1 | C505: 97.2 | D505: 68.4044 | F505: 22115 | G505: 24320 | H505: 5.0461074 | I505: 27699 | J505: 905.8 | K505: 674 | L505: 328.39632 | M505: 951.8 | U505: 24.615
A506: 37134 | B506: 74.3 | C506: 98.3 | D506: 68.4794 | F506: 21732 | G506: 24820 | H506: 5.0784193 | I506: 27719 | J506: 906.4 | K506: 663 | L506: 330.72633 | M506: 951.2 | U506: 25.673043
A507: 37164 | B507: 74.2 | C507: 97.8 | D507: 68.5095 | F507: 21426 | G507: 23532 | H507: 5.092117 | I507: 27715 | J507: 904.9 | K507: 663 | L507: 331.10736 | M507: 946.1 | U507: 25.5115
A508: 37195 | B508: 74.4 | C508: 97.2 | D508: 68.8234 | F508: 22806 | G508: 24848 | H508: 5.0886319 | I508: 27735 | J508: 904.2 | K508: 639 | L508: 332.70195 | M508: 953 | U508: 20.452174
A509: 37225 | B509: 74.4 | C509: 97.3 | D509: 68.7432 | F509: 22025 | G509: 24191 | H509: 5.1055256 | I509: 27787 | J509: 903.5 | K509: 626 | L509: 333.7407 | M509: 959.7 | U509: 18.914091
A510: 37256 | B510: 74.3 | C510: 96.9 | D510: 68.6953 | F510: 21049 | G510: 23801 | H510: 5.1836442 | I510: 27803 | J510: 903.5 | K510: 602 | L510: 334.15437 | M510: 966.5 | U510: 18.531429
A511: 37287 | B511: 74.5 | C511: 96.3 | D511: 68.9917 | F511: 22703 | G511: 24581 | H511: 5.1831871 | I511: 27769 | J511: 899.7 | K511: 605 | L511: 332.56489 | M511: 958.2 | U511: 19.462609
A512: 37315 | B512: 74.4 | C512: 96.4 | D512: 68.8412 | F512: 22397 | G512: 25339 | H512: 5.1486906 | I512: 27781 | J512: 900.1 | K512: 616 | L512: 334.08736 | M512: 951.9 | U512: 20.111
A513: 37346 | B513: 74.6 | C513: 98.2 | D513: 68.7459 | F513: 22615 | G513: 25448 | H513: 5.1685317 | I513: 27797 | J513: 901.5 | K513: 617 | L513: 334.31133 | M513: 947.5 | U513: 23.84381
A514: 37376 | B514: 75 | C514: 96.1 | D514: 69.7015 | F514: 23208 | G514: 26560 | H514: 5.1807475 | I514: 27856 | J514: 903.9 | K514: 622 | L514: 338.34114 | M514: 954.9 | U514: 25.598182
A515: 37407 | B515: 75.5 | C515: 99.1 | D515: 69.8082 | F515: 25099 | G515: 26852 | H515: 5.2395515 | I515: 27888 | J515: 908.3 | K515: 613 | L515: 338.78087 | M515: 947.1 | U515: 25.33913
...

Sheet MonthlyData
A1: 1960 | B1: GDP | C1: Production, Services, Trade | G1: Labour market | M1: Prices
A2: 2021 | B2: UK GDP monthly, SA | C2: UK INDEX OF PRODUCTION - ALL PRODUCTION INDUSTRIES VOLA | D2: UK INDEX OF SERVICES - TOTAL VOLA | E2: UK ITS EXPORTS F.O.B. TOTAL CURA | F2: UK ITS IMPORTS C.I.F. TOTAL CURA | G2: UK LFS: UNEMPLOYMENT RATE, ALL, AGED 16 & OVER SADJ | H2: UK LFS: IN EMPLOYMENT, ALL, AGED 16-64 VOLA | I2: HOURS WORKED | J2: UK JOB VACANCIES (STANDARDIZED) VOLA | K2: Average Weekly Earnings | L2: Claimant Count Rate | M2: CPI all items | N2: Core CPI | O2: RPI all items | P2: RPI ex Mortgages Interest Payments (RPIX) | Q2: PPI Output | R2: PPI Input | S2: Nationwide House Price MoM | T2: Oil Brent
A3: count | B3: 1 | C3: 9 | D3: 10 | E3: 11 | F3: 12 | G3: 13 | H3: 14 | I3: 15 | J3: 16 | K3: 17 | L3: 18 | M3: 19 | N3: 20 | O3: 21 | P3: 22 | Q3: 23 | R3: 24 | S3: 25 | T3: 26
A4: m | B4: GDP_M | C4: IoP | D4: IoS | E4: Exp | F4: Imp | G4: UR | H4: EMP | I4: Hours | J4: Vacancies | K4: AWE | L4: Claimant | M4: CPI | N4: CoreCPI | O4: RPI | P4: RPIX | Q4: PPIout | R4: PPIin | S4: HPr | T4: Oil
A5: transform | B5: 3 | C5: 3 | D5: 3 | E5: 3 | F5: 3 | G5: 0 | H5: 3 | I5: 3 | J5: 3 | K5: 3 | L5: 0 | M5: 3 | N5: 3 | O5: 3 | P5: 3 | Q5: 3 | R5: 3 | S5: 2 | T5: 3
A6: =IF(MonthlyFAME!A8=0,"",MonthlyFAME!A8) -> 21975 | B6: =IF(MonthlyFAME!B8=0,"",MonthlyFAME!B8) | C6: =IF(MonthlyFAME!C8=0,"",MonthlyFAME!C8) -> 41.3 | D6: =IF(MonthlyFAME!D8=0,"",MonthlyFAME!D8) | E6: =IF(MonthlyFAME!F8=0,"",MonthlyFAME!F8) | F6: =IF(MonthlyFAME!G8=0,"",MonthlyFAME!G8) | G6: =IF(MonthlyFAME!H8=0,"",MonthlyFAME!H8) | H6: =IF(MonthlyFAME!I8=0,"",MonthlyFAME!I8) | I6: =IF(MonthlyFAME!J8=0,"",MonthlyFAME!J8) | K6: =IF(MonthlyFAME!L8=0,"",MonthlyFAME!L8) | L6: =IF(MonthlyFAME!M8=0,"",MonthlyFAME!M8) | M6: =IF(MonthlyFAME!N8=0,"",MonthlyFAME!N8) | N6: =IF(MonthlyFAME!O8=0,"",MonthlyFAME!O8) | O6: =IF(MonthlyFAME!P8=0,"",MonthlyFAME!P8) | P6: =IF(MonthlyFAME!Q8=0,"",MonthlyFAME!Q8) | Q6: =IF(MonthlyFAME!R8=0,"",MonthlyFAME!R8) | R6: =IF(MonthlyFAME!S8=0,"",MonthlyFAME!S8) | ... T6: =IF(MonthlyFAME!U8=0,"",MonthlyFAME!U8)
A7: =IF(MonthlyFAME!A9=0,"",MonthlyFAME!A9) -> 22006 | B7: =IF(MonthlyFAME!B9=0,"",MonthlyFAME!B9) | C7: =IF(MonthlyFAME!C9=0,"",MonthlyFAME!C9) -> 41.3 | D7: =IF(MonthlyFAME!D9=0,"",MonthlyFAME!D9) | E7: =IF(MonthlyFAME!F9=0,"",MonthlyFAME!F9) | F7: =IF(MonthlyFAME!G9=0,"",MonthlyFAME!G9) | G7: =IF(MonthlyFAME!H9=0,"",MonthlyFAME!H9) | H7: =IF(MonthlyFAME!I9=0,"",MonthlyFAME!I9) | I7: =IF(MonthlyFAME!J9=0,"",MonthlyFAME!J9) | K7: =IF(MonthlyFAME!L9=0,"",MonthlyFAME!L9) | L7: =IF(MonthlyFAME!M9=0,"",MonthlyFAME!M9) | M7: =IF(MonthlyFAME!N9=0,"",MonthlyFAME!N9) | N7: =IF(MonthlyFAME!O9=0,"",MonthlyFAME!O9) | O7: =IF(MonthlyFAME!P9=0,"",MonthlyFAME!P9) | P7: =IF(MonthlyFAME!Q9=0,"",MonthlyFAME!Q9) | Q7: =IF(MonthlyFAME!R9=0,"",MonthlyFAME!R9) | R7: =IF(MonthlyFAME!S9=0,"",MonthlyFAME!S9) | ... T7: =IF(MonthlyFAME!U9=0,"",MonthlyFAME!U9)
A8: =IF(MonthlyFAME!A10=0,"",MonthlyFAME!A10) -> 22036 | B8: =IF(MonthlyFAME!B10=0,"",MonthlyFAME!B10) | C8: =IF(MonthlyFAME!C10=0,"",MonthlyFAME!C10) -> 41.3 | D8: =IF(MonthlyFAME!D10=0,"",MonthlyFAME!D10) | E8: =IF(MonthlyFAME!F10=0,"",MonthlyFAME!F10) | F8: =IF(MonthlyFAME!G10=0,"",MonthlyFAME!G10) | G8: =IF(MonthlyFAME!H10=0,"",MonthlyFAME!H10) | H8: =IF(MonthlyFAME!I10=0,"",MonthlyFAME!I10) | I8: =IF(MonthlyFAME!J10=0,"",MonthlyFAME!J10) | K8: =IF(MonthlyFAME!L10=0,"",MonthlyFAME!L10) | L8: =IF(MonthlyFAME!M10=0,"",MonthlyFAME!M10) | M8: =IF(MonthlyFAME!N10=0,"",MonthlyFAME!N10) | N8: =IF(MonthlyFAME!O10=0,"",MonthlyFAME!O10) | O8: =IF(MonthlyFAME!P10=0,"",MonthlyFAME!P10) | P8: =IF(MonthlyFAME!Q10=0,"",MonthlyFAME!Q10) | Q8: =IF(MonthlyFAME!R10=0,"",MonthlyFAME!R10) | R8: =IF(MonthlyFAME!S10=0,"",MonthlyFAME!S10) | ... T8: =IF(MonthlyFAME!U10=0,"",MonthlyFAME!U10) | V8: Transform
A9: =IF(MonthlyFAME!A11=0,"",MonthlyFAME!A11) -> 22067 | B9: =IF(MonthlyFAME!B11=0,"",MonthlyFAME!B11) | C9: =IF(MonthlyFAME!C11=0,"",MonthlyFAME!C11) -> 41.3 | D9: =IF(MonthlyFAME!D11=0,"",MonthlyFAME!D11) | E9: =IF(MonthlyFAME!F11=0,"",MonthlyFAME!F11) | F9: =IF(MonthlyFAME!G11=0,"",MonthlyFAME!G11) | G9: =IF(MonthlyFAME!H11=0,"",MonthlyFAME!H11) | H9: =IF(MonthlyFAME!I11=0,"",MonthlyFAME!I11) | I9: =IF(MonthlyFAME!J11=0,"",MonthlyFAME!J11) | K9: =IF(MonthlyFAME!L11=0,"",MonthlyFAME!L11) | L9: =IF(MonthlyFAME!M11=0,"",MonthlyFAME!M11) | M9: =IF(MonthlyFAME!N11=0,"",MonthlyFAME!N11) | N9: =IF(MonthlyFAME!O11=0,"",MonthlyFAME!O11) | O9: =IF(MonthlyFAME!P11=0,"",MonthlyFAME!P11) | P9: =IF(MonthlyFAME!Q11=0,"",MonthlyFAME!Q11) | Q9: =IF(MonthlyFAME!R11=0,"",MonthlyFAME!R11) | R9: =IF(MonthlyFAME!S11=0,"",MonthlyFAME!S11) | ... T9: =IF(MonthlyFAME!U11=0,"",MonthlyFAME!U11) | V9: 0 | W9: no transform
A10: =IF(MonthlyFAME!A12=0,"",MonthlyFAME!A12) -> 22097 | B10: =IF(MonthlyFAME!B12=0,"",MonthlyFAME!B12) | C10: =IF(MonthlyFAME!C12=0,"",MonthlyFAME!C12) -> 41.3 | D10: =IF(MonthlyFAME!D12=0,"",MonthlyFAME!D12) | E10: =IF(MonthlyFAME!F12=0,"",MonthlyFAME!F12) | F10: =IF(MonthlyFAME!G12=0,"",MonthlyFAME!G12) | G10: =IF(MonthlyFAME!H12=0,"",MonthlyFAME!H12) | H10: =IF(MonthlyFAME!I12=0,"",MonthlyFAME!I12) | I10: =IF(MonthlyFAME!J12=0,"",MonthlyFAME!J12) | K10: =IF(MonthlyFAME!L12=0,"",MonthlyFAME!L12) | L10: =IF(MonthlyFAME!M12=0,"",MonthlyFAME!M12) | M10: =IF(MonthlyFAME!N12=0,"",MonthlyFAME!N12) | N10: =IF(MonthlyFAME!O12=0,"",MonthlyFAME!O12) | O10: =IF(MonthlyFAME!P12=0,"",MonthlyFAME!P12) | P10: =IF(MonthlyFAME!Q12=0,"",MonthlyFAME!Q12) | Q10: =IF(MonthlyFAME!R12=0,"",MonthlyFAME!R12) | R10: =IF(MonthlyFAME!S12=0,"",MonthlyFAME!S12) | ... T10: =IF(MonthlyFAME!U12=0,"",MonthlyFAME!U12) | V10: 1 | W10: log
A11: =IF(MonthlyFAME!A13=0,"",MonthlyFAME!A13) -> 22128 | B11: =IF(MonthlyFAME!B13=0,"",MonthlyFAME!B13) | C11: =IF(MonthlyFAME!C13=0,"",MonthlyFAME!C13) -> 41.3 | D11: =IF(MonthlyFAME!D13=0,"",MonthlyFAME!D13) | E11: =IF(MonthlyFAME!F13=0,"",MonthlyFAME!F13) | F11: =IF(MonthlyFAME!G13=0,"",MonthlyFAME!G13) | G11: =IF(MonthlyFAME!H13=0,"",MonthlyFAME!H13) | H11: =IF(MonthlyFAME!I13=0,"",MonthlyFAME!I13) | I11: =IF(MonthlyFAME!J13=0,"",MonthlyFAME!J13) | K11: =IF(MonthlyFAME!L13=0,"",MonthlyFAME!L13) | L11: =IF(MonthlyFAME!M13=0,"",MonthlyFAME!M13) | M11: =IF(MonthlyFAME!N13=0,"",MonthlyFAME!N13) | N11: =IF(MonthlyFAME!O13=0,"",MonthlyFAME!O13) | O11: =IF(MonthlyFAME!P13=0,"",MonthlyFAME!P13) | P11: =IF(MonthlyFAME!Q13=0,"",MonthlyFAME!Q13) | Q11: =IF(MonthlyFAME!R13=0,"",MonthlyFAME!R13) | R11: =IF(MonthlyFAME!S13=0,"",MonthlyFAME!S13) | ... T11: =IF(MonthlyFAME!U13=0,"",MonthlyFAME!U13) | V11: 2 | W11: first diff
A12: =IF(MonthlyFAME!A14=0,"",MonthlyFAME!A14) -> 22159 | B12: =IF(MonthlyFAME!B14=0,"",MonthlyFAME!B14) | C12: =IF(MonthlyFAME!C14=0,"",MonthlyFAME!C14) -> 41.4 | D12: =IF(MonthlyFAME!D14=0,"",MonthlyFAME!D14) | E12: =IF(MonthlyFAME!F14=0,"",MonthlyFAME!F14) | F12: =IF(MonthlyFAME!G14=0,"",MonthlyFAME!G14) | G12: =IF(MonthlyFAME!H14=0,"",MonthlyFAME!H14) | H12: =IF(MonthlyFAME!I14=0,"",MonthlyFAME!I14) | I12: =IF(MonthlyFAME!J14=0,"",MonthlyFAME!J14) | K12: =IF(MonthlyFAME!L14=0,"",MonthlyFAME!L14) | L12: =IF(MonthlyFAME!M14=0,"",MonthlyFAME!M14) | M12: =IF(MonthlyFAME!N14=0,"",MonthlyFAME!N14) | N12: =IF(MonthlyFAME!O14=0,"",MonthlyFAME!O14) | O12: =IF(MonthlyFAME!P14=0,"",MonthlyFAME!P14) | P12: =IF(MonthlyFAME!Q14=0,"",MonthlyFAME!Q14) | Q12: =IF(MonthlyFAME!R14=0,"",MonthlyFAME!R14) | R12: =IF(MonthlyFAME!S14=0,"",MonthlyFAME!S14) | ... T12: =IF(MonthlyFAME!U14=0,"",MonthlyFAME!U14) | V12: 3 | W12: log first diff
A13: =IF(MonthlyFAME!A15=0,"",MonthlyFAME!A15) -> 22189 | B13: =IF(MonthlyFAME!B15=0,"",MonthlyFAME!B15) | C13: =IF(MonthlyFAME!C15=0,"",MonthlyFAME!C15) -> 41.7 | D13: =IF(MonthlyFAME!D15=0,"",MonthlyFAME!D15) | E13: =IF(MonthlyFAME!F15=0,"",MonthlyFAME!F15) | F13: =IF(MonthlyFAME!G15=0,"",MonthlyFAME!G15) | G13: =IF(MonthlyFAME!H15=0,"",MonthlyFAME!H15) | H13: =IF(MonthlyFAME!I15=0,"",MonthlyFAME!I15) | I13: =IF(MonthlyFAME!J15=0,"",MonthlyFAME!J15) | K13: =IF(MonthlyFAME!L15=0,"",MonthlyFAME!L15) | L13: =IF(MonthlyFAME!M15=0,"",MonthlyFAME!M15) | M13: =IF(MonthlyFAME!N15=0,"",MonthlyFAME!N15) | N13: =IF(MonthlyFAME!O15=0,"",MonthlyFAME!O15) | O13: =IF(MonthlyFAME!P15=0,"",MonthlyFAME!P15) | P13: =IF(MonthlyFAME!Q15=0,"",MonthlyFAME!Q15) | Q13: =IF(MonthlyFAME!R15=0,"",MonthlyFAME!R15) | R13: =IF(MonthlyFAME!S15=0,"",MonthlyFAME!S15) | ... T13: =IF(MonthlyFAME!U15=0,"",MonthlyFAME!U15) | V13: 4 | W13: y-o-y log diff
A14: =IF(MonthlyFAME!A16=0,"",MonthlyFAME!A16) -> 22220 | B14: =IF(MonthlyFAME!B16=0,"",MonthlyFAME!B16) | C14: =IF(MonthlyFAME!C16=0,"",MonthlyFAME!C16) -> 41.9 | D14: =IF(MonthlyFAME!D16=0,"",MonthlyFAME!D16) | E14: =IF(MonthlyFAME!F16=0,"",MonthlyFAME!F16) | F14: =IF(MonthlyFAME!G16=0,"",MonthlyFAME!G16) | G14: =IF(MonthlyFAME!H16=0,"",MonthlyFAME!H16) | H14: =IF(MonthlyFAME!I16=0,"",MonthlyFAME!I16) | I14: =IF(MonthlyFAME!J16=0,"",MonthlyFAME!J16) | K14: =IF(MonthlyFAME!L16=0,"",MonthlyFAME!L16) | L14: =IF(MonthlyFAME!M16=0,"",MonthlyFAME!M16) | M14: =IF(MonthlyFAME!N16=0,"",MonthlyFAME!N16) | N14: =IF(MonthlyFAME!O16=0,"",MonthlyFAME!O16) | O14: =IF(MonthlyFAME!P16=0,"",MonthlyFAME!P16) | P14: =IF(MonthlyFAME!Q16=0,"",MonthlyFAME!Q16) | Q14: =IF(MonthlyFAME!R16=0,"",MonthlyFAME!R16) | R14: =IF(MonthlyFAME!S16=0,"",MonthlyFAME!S16) | ... T14: =IF(MonthlyFAME!U16=0,"",MonthlyFAME!U16)
A15: =IF(MonthlyFAME!A17=0,"",MonthlyFAME!A17) -> 22250 | B15: =IF(MonthlyFAME!B17=0,"",MonthlyFAME!B17) | C15: =IF(MonthlyFAME!C17=0,"",MonthlyFAME!C17) -> 41.9 | D15: =IF(MonthlyFAME!D17=0,"",MonthlyFAME!D17) | E15: =IF(MonthlyFAME!F17=0,"",MonthlyFAME!F17) | F15: =IF(MonthlyFAME!G17=0,"",MonthlyFAME!G17) | G15: =IF(MonthlyFAME!H17=0,"",MonthlyFAME!H17) | H15: =IF(MonthlyFAME!I17=0,"",MonthlyFAME!I17) | I15: =IF(MonthlyFAME!J17=0,"",MonthlyFAME!J17) | K15: =IF(MonthlyFAME!L17=0,"",MonthlyFAME!L17) | L15: =IF(MonthlyFAME!M17=0,"",MonthlyFAME!M17) | M15: =IF(MonthlyFAME!N17=0,"",MonthlyFAME!N17) | N15: =IF(MonthlyFAME!O17=0,"",MonthlyFAME!O17) | O15: =IF(MonthlyFAME!P17=0,"",MonthlyFAME!P17) | P15: =IF(MonthlyFAME!Q17=0,"",MonthlyFAME!Q17) | Q15: =IF(MonthlyFAME!R17=0,"",MonthlyFAME!R17) | R15: =IF(MonthlyFAME!S17=0,"",MonthlyFAME!S17) | ... T15: =IF(MonthlyFAME!U17=0,"",MonthlyFAME!U17)
A16: =IF(MonthlyFAME!A18=0,"",MonthlyFAME!A18) -> 22281 | B16: =IF(MonthlyFAME!B18=0,"",MonthlyFAME!B18) | C16: =IF(MonthlyFAME!C18=0,"",MonthlyFAME!C18) -> 41.7 | D16: =IF(MonthlyFAME!D18=0,"",MonthlyFAME!D18) | E16: =IF(MonthlyFAME!F18=0,"",MonthlyFAME!F18) | F16: =IF(MonthlyFAME!G18=0,"",MonthlyFAME!G18) | G16: =IF(MonthlyFAME!H18=0,"",MonthlyFAME!H18) | H16: =IF(MonthlyFAME!I18=0,"",MonthlyFAME!I18) | I16: =IF(MonthlyFAME!J18=0,"",MonthlyFAME!J18) | K16: =IF(MonthlyFAME!L18=0,"",MonthlyFAME!L18) | L16: =IF(MonthlyFAME!M18=0,"",MonthlyFAME!M18) | M16: =IF(MonthlyFAME!N18=0,"",MonthlyFAME!N18) | N16: =IF(MonthlyFAME!O18=0,"",MonthlyFAME!O18) | O16: =IF(MonthlyFAME!P18=0,"",MonthlyFAME!P18) | P16: =IF(MonthlyFAME!Q18=0,"",MonthlyFAME!Q18) | Q16: =IF(MonthlyFAME!R18=0,"",MonthlyFAME!R18) | R16: =IF(MonthlyFAME!S18=0,"",MonthlyFAME!S18) | ... T16: =IF(MonthlyFAME!U18=0,"",MonthlyFAME!U18)
A17: =IF(MonthlyFAME!A19=0,"",MonthlyFAME!A19) -> 22312 | B17: =IF(MonthlyFAME!B19=0,"",MonthlyFAME!B19) | C17: =IF(MonthlyFAME!C19=0,"",MonthlyFAME!C19) -> 41.3 | D17: =IF(MonthlyFAME!D19=0,"",MonthlyFAME!D19) | E17: =IF(MonthlyFAME!F19=0,"",MonthlyFAME!F19) | F17: =IF(MonthlyFAME!G19=0,"",MonthlyFAME!G19) | G17: =IF(MonthlyFAME!H19=0,"",MonthlyFAME!H19) | H17: =IF(MonthlyFAME!I19=0,"",MonthlyFAME!I19) | I17: =IF(MonthlyFAME!J19=0,"",MonthlyFAME!J19) | K17: =IF(MonthlyFAME!L19=0,"",MonthlyFAME!L19) | L17: =IF(MonthlyFAME!M19=0,"",MonthlyFAME!M19) | M17: =IF(MonthlyFAME!N19=0,"",MonthlyFAME!N19) | N17: =IF(MonthlyFAME!O19=0,"",MonthlyFAME!O19) | O17: =IF(MonthlyFAME!P19=0,"",MonthlyFAME!P19) | P17: =IF(MonthlyFAME!Q19=0,"",MonthlyFAME!Q19) | Q17: =IF(MonthlyFAME!R19=0,"",MonthlyFAME!R19) | R17: =IF(MonthlyFAME!S19=0,"",MonthlyFAME!S19) | ... T17: =IF(MonthlyFAME!U19=0,"",MonthlyFAME!U19)
A18: =IF(MonthlyFAME!A20=0,"",MonthlyFAME!A20) -> 22340 | B18: =IF(MonthlyFAME!B20=0,"",MonthlyFAME!B20) | C18: =IF(MonthlyFAME!C20=0,"",MonthlyFAME!C20) -> 41.1 | D18: =IF(MonthlyFAME!D20=0,"",MonthlyFAME!D20) | E18: =IF(MonthlyFAME!F20=0,"",MonthlyFAME!F20) | F18: =IF(MonthlyFAME!G20=0,"",MonthlyFAME!G20) | G18: =IF(MonthlyFAME!H20=0,"",MonthlyFAME!H20) | H18: =IF(MonthlyFAME!I20=0,"",MonthlyFAME!I20) | I18: =IF(MonthlyFAME!J20=0,"",MonthlyFAME!J20) | K18: =IF(MonthlyFAME!L20=0,"",MonthlyFAME!L20) | L18: =IF(MonthlyFAME!M20=0,"",MonthlyFAME!M20) | M18: =IF(MonthlyFAME!N20=0,"",MonthlyFAME!N20) | N18: =IF(MonthlyFAME!O20=0,"",MonthlyFAME!O20) | O18: =IF(MonthlyFAME!P20=0,"",MonthlyFAME!P20) | P18: =IF(MonthlyFAME!Q20=0,"",MonthlyFAME!Q20) | Q18: =IF(MonthlyFAME!R20=0,"",MonthlyFAME!R20) | R18: =IF(MonthlyFAME!S20=0,"",MonthlyFAME!S20) | ... T18: =IF(MonthlyFAME!U20=0,"",MonthlyFAME!U20)
A19: =IF(MonthlyFAME!A21=0,"",MonthlyFAME!A21) -> 22371 | B19: =IF(MonthlyFAME!B21=0,"",MonthlyFAME!B21) | C19: =IF(MonthlyFAME!C21=0,"",MonthlyFAME!C21) -> 41.3 | D19: =IF(MonthlyFAME!D21=0,"",MonthlyFAME!D21) | E19: =IF(MonthlyFAME!F21=0,"",MonthlyFAME!F21) | F19: =IF(MonthlyFAME!G21=0,"",MonthlyFAME!G21) | G19: =IF(MonthlyFAME!H21=0,"",MonthlyFAME!H21) | H19: =IF(MonthlyFAME!I21=0,"",MonthlyFAME!I21) | I19: =IF(MonthlyFAME!J21=0,"",MonthlyFAME!J21) | K19: =IF(MonthlyFAME!L21=0,"",MonthlyFAME!L21) | L19: =IF(MonthlyFAME!M21=0,"",MonthlyFAME!M21) | M19: =IF(MonthlyFAME!N21=0,"",MonthlyFAME!N21) | N19: =IF(MonthlyFAME!O21=0,"",MonthlyFAME!O21) | O19: =IF(MonthlyFAME!P21=0,"",MonthlyFAME!P21) | P19: =IF(MonthlyFAME!Q21=0,"",MonthlyFAME!Q21) | Q19: =IF(MonthlyFAME!R21=0,"",MonthlyFAME!R21) | R19: =IF(MonthlyFAME!S21=0,"",MonthlyFAME!S21) | ... T19: =IF(MonthlyFAME!U21=0,"",MonthlyFAME!U21)
A20: =IF(MonthlyFAME!A22=0,"",MonthlyFAME!A22) -> 22401 | B20: =IF(MonthlyFAME!B22=0,"",MonthlyFAME!B22) | C20: =IF(MonthlyFAME!C22=0,"",MonthlyFAME!C22) -> 41.7 | D20: =IF(MonthlyFAME!D22=0,"",MonthlyFAME!D22) | E20: =IF(MonthlyFAME!F22=0,"",MonthlyFAME!F22) | F20: =IF(MonthlyFAME!G22=0,"",MonthlyFAME!G22) | G20: =IF(MonthlyFAME!H22=0,"",MonthlyFAME!H22) | H20: =IF(MonthlyFAME!I22=0,"",MonthlyFAME!I22) | I20: =IF(MonthlyFAME!J22=0,"",MonthlyFAME!J22) | K20: =IF(MonthlyFAME!L22=0,"",MonthlyFAME!L22) | L20: =IF(MonthlyFAME!M22=0,"",MonthlyFAME!M22) | M20: =IF(MonthlyFAME!N22=0,"",MonthlyFAME!N22) | N20: =IF(MonthlyFAME!O22=0,"",MonthlyFAME!O22) | O20: =IF(MonthlyFAME!P22=0,"",MonthlyFAME!P22) | P20: =IF(MonthlyFAME!Q22=0,"",MonthlyFAME!Q22) | Q20: =IF(MonthlyFAME!R22=0,"",MonthlyFAME!R22) | R20: =IF(MonthlyFAME!S22=0,"",MonthlyFAME!S22) | ... T20: =IF(MonthlyFAME!U22=0,"",MonthlyFAME!U22)
A21: =IF(MonthlyFAME!A23=0,"",MonthlyFAME!A23) -> 22432 | B21: =IF(MonthlyFAME!B23=0,"",MonthlyFAME!B23) | C21: =IF(MonthlyFAME!C23=0,"",MonthlyFAME!C23) -> 42 | D21: =IF(MonthlyFAME!D23=0,"",MonthlyFAME!D23) | E21: =IF(MonthlyFAME!F23=0,"",MonthlyFAME!F23) | F21: =IF(MonthlyFAME!G23=0,"",MonthlyFAME!G23) | G21: =IF(MonthlyFAME!H23=0,"",MonthlyFAME!H23) | H21: =IF(MonthlyFAME!I23=0,"",MonthlyFAME!I23) | I21: =IF(MonthlyFAME!J23=0,"",MonthlyFAME!J23) | K21: =IF(MonthlyFAME!L23=0,"",MonthlyFAME!L23) | L21: =IF(MonthlyFAME!M23=0,"",MonthlyFAME!M23) | M21: =IF(MonthlyFAME!N23=0,"",MonthlyFAME!N23) | N21: =IF(MonthlyFAME!O23=0,"",MonthlyFAME!O23) | O21: =IF(MonthlyFAME!P23=0,"",MonthlyFAME!P23) | P21: =IF(MonthlyFAME!Q23=0,"",MonthlyFAME!Q23) | Q21: =IF(MonthlyFAME!R23=0,"",MonthlyFAME!R23) | R21: =IF(MonthlyFAME!S23=0,"",MonthlyFAME!S23) | ... T21: =IF(MonthlyFAME!U23=0,"",MonthlyFAME!U23)
A22: =IF(MonthlyFAME!A24=0,"",MonthlyFAME!A24) -> 22462 | B22: =IF(MonthlyFAME!B24=0,"",MonthlyFAME!B24) | C22: =IF(MonthlyFAME!C24=0,"",MonthlyFAME!C24) -> 42.1 | D22: =IF(MonthlyFAME!D24=0,"",MonthlyFAME!D24) | E22: =IF(MonthlyFAME!F24=0,"",MonthlyFAME!F24) | F22: =IF(MonthlyFAME!G24=0,"",MonthlyFAME!G24) | G22: =IF(MonthlyFAME!H24=0,"",MonthlyFAME!H24) | H22: =IF(MonthlyFAME!I24=0,"",MonthlyFAME!I24) | I22: =IF(MonthlyFAME!J24=0,"",MonthlyFAME!J24) | K22: =IF(MonthlyFAME!L24=0,"",MonthlyFAME!L24) | L22: =IF(MonthlyFAME!M24=0,"",MonthlyFAME!M24) | M22: =IF(MonthlyFAME!N24=0,"",MonthlyFAME!N24) | N22: =IF(MonthlyFAME!O24=0,"",MonthlyFAME!O24) | O22: =IF(MonthlyFAME!P24=0,"",MonthlyFAME!P24) | P22: =IF(MonthlyFAME!Q24=0,"",MonthlyFAME!Q24) | Q22: =IF(MonthlyFAME!R24=0,"",MonthlyFAME!R24) | R22: =IF(MonthlyFAME!S24=0,"",MonthlyFAME!S24) | ... T22: =IF(MonthlyFAME!U24=0,"",MonthlyFAME!U24)
A23: =IF(MonthlyFAME!A25=0,"",MonthlyFAME!A25) -> 22493 | B23: =IF(MonthlyFAME!B25=0,"",MonthlyFAME!B25) | C23: =IF(MonthlyFAME!C25=0,"",MonthlyFAME!C25) -> 41.9 | D23: =IF(MonthlyFAME!D25=0,"",MonthlyFAME!D25) | E23: =IF(MonthlyFAME!F25=0,"",MonthlyFAME!F25) | F23: =IF(MonthlyFAME!G25=0,"",MonthlyFAME!G25) | G23: =IF(MonthlyFAME!H25=0,"",MonthlyFAME!H25) | H23: =IF(MonthlyFAME!I25=0,"",MonthlyFAME!I25) | I23: =IF(MonthlyFAME!J25=0,"",MonthlyFAME!J25) | K23: =IF(MonthlyFAME!L25=0,"",MonthlyFAME!L25) | L23: =IF(MonthlyFAME!M25=0,"",MonthlyFAME!M25) | M23: =IF(MonthlyFAME!N25=0,"",MonthlyFAME!N25) | N23: =IF(MonthlyFAME!O25=0,"",MonthlyFAME!O25) | O23: =IF(MonthlyFAME!P25=0,"",MonthlyFAME!P25) | P23: =IF(MonthlyFAME!Q25=0,"",MonthlyFAME!Q25) | Q23: =IF(MonthlyFAME!R25=0,"",MonthlyFAME!R25) | R23: =IF(MonthlyFAME!S25=0,"",MonthlyFAME!S25) | ... T23: =IF(MonthlyFAME!U25=0,"",MonthlyFAME!U25)
A24: =IF(MonthlyFAME!A26=0,"",MonthlyFAME!A26) -> 22524 | B24: =IF(MonthlyFAME!B26=0,"",MonthlyFAME!B26) | C24: =IF(MonthlyFAME!C26=0,"",MonthlyFAME!C26) -> 41.7 | D24: =IF(MonthlyFAME!D26=0,"",MonthlyFAME!D26) | E24: =IF(MonthlyFAME!F26=0,"",MonthlyFAME!F26) | F24: =IF(MonthlyFAME!G26=0,"",MonthlyFAME!G26) | G24: =IF(MonthlyFAME!H26=0,"",MonthlyFAME!H26) | H24: =IF(MonthlyFAME!I26=0,"",MonthlyFAME!I26) | I24: =IF(MonthlyFAME!J26=0,"",MonthlyFAME!J26) | K24: =IF(MonthlyFAME!L26=0,"",MonthlyFAME!L26) | L24: =IF(MonthlyFAME!M26=0,"",MonthlyFAME!M26) | M24: =IF(MonthlyFAME!N26=0,"",MonthlyFAME!N26) | N24: =IF(MonthlyFAME!O26=0,"",MonthlyFAME!O26) | O24: =IF(MonthlyFAME!P26=0,"",MonthlyFAME!P26) | P24: =IF(MonthlyFAME!Q26=0,"",MonthlyFAME!Q26) | Q24: =IF(MonthlyFAME!R26=0,"",MonthlyFAME!R26) | R24: =IF(MonthlyFAME!S26=0,"",MonthlyFAME!S26) | ... T24: =IF(MonthlyFAME!U26=0,"",MonthlyFAME!U26)
A25: =IF(MonthlyFAME!A27=0,"",MonthlyFAME!A27) -> 22554 | B25: =IF(MonthlyFAME!B27=0,"",MonthlyFAME!B27) | C25: =IF(MonthlyFAME!C27=0,"",MonthlyFAME!C27) -> 41.6 | D25: =IF(MonthlyFAME!D27=0,"",MonthlyFAME!D27) | E25: =IF(MonthlyFAME!F27=0,"",MonthlyFAME!F27) | F25: =IF(MonthlyFAME!G27=0,"",MonthlyFAME!G27) | G25: =IF(MonthlyFAME!H27=0,"",MonthlyFAME!H27) | H25: =IF(MonthlyFAME!I27=0,"",MonthlyFAME!I27) | I25: =IF(MonthlyFAME!J27=0,"",MonthlyFAME!J27) | K25: =IF(MonthlyFAME!L27=0,"",MonthlyFAME!L27) | L25: =IF(MonthlyFAME!M27=0,"",MonthlyFAME!M27) | M25: =IF(MonthlyFAME!N27=0,"",MonthlyFAME!N27) | N25: =IF(MonthlyFAME!O27=0,"",MonthlyFAME!O27) | O25: =IF(MonthlyFAME!P27=0,"",MonthlyFAME!P27) | P25: =IF(MonthlyFAME!Q27=0,"",MonthlyFAME!Q27) | Q25: =IF(MonthlyFAME!R27=0,"",MonthlyFAME!R27) | R25: =IF(MonthlyFAME!S27=0,"",MonthlyFAME!S27) | ... T25: =IF(MonthlyFAME!U27=0,"",MonthlyFAME!U27)
... A415: =IF(MonthlyFAME!A417=0,"",MonthlyFAME!A417) -> 34424 | B415: =IF(MonthlyFAME!B417=0,"",MonthlyFAME!B417) | C415: =IF(MonthlyFAME!C417=0,"",MonthlyFAME!C417) -> 76.8 | D415: =IF(MonthlyFAME!D417=0,"",MonthlyFAME!D417) | E415: =IF(MonthlyFAME!F417=0,"",MonthlyFAME!F417) -> 10671 | F415: =IF(MonthlyFAME!G417=0,"",MonthlyFAME!G417) -> 11675 | G415: =IF(MonthlyFAME!H417=0,"",MonthlyFAME!H417) -> 9.9454172 | H415: =IF(MonthlyFAME!I417=0,"",MonthlyFAME!I417) -> 25408 | I415: =IF(MonthlyFAME!J417=0,"",MonthlyFAME!J417) -> 837.1 | K415: =IF(MonthlyFAME!L417=0,"",MonthlyFAME!L417) -> 241.03294 | L415: =IF(MonthlyFAME!M417=0,"",MonthlyFAME!M417) -> 2712 | M415: =IF(MonthlyFAME!N417=0,"",MonthlyFAME!N417) | N415: =IF(MonthlyFAME!O417=0,"",MonthlyFAME!O417) | O415: =IF(MonthlyFAME!P417=0,"",MonthlyFAME!P417) | P415: =IF(MonthlyFAME!Q417=0,"",MonthlyFAME!Q417) | Q415: =IF(MonthlyFAME!R417=0,"",MonthlyFAME!R417) | R415: =IF(MonthlyFAME!S417=0,"",MonthlyFAME!S417) | ... T415: =IF(MonthlyFAME!U417=0,"",MonthlyFAME!U417) -> 13.892174
A416: =IF(MonthlyFAME!A418=0,"",MonthlyFAME!A418) -> 34454 | B416: =IF(MonthlyFAME!B418=0,"",MonthlyFAME!B418) | C416: =IF(MonthlyFAME!C418=0,"",MonthlyFAME!C418) -> 77.8 | E416: =IF(MonthlyFAME!F418=0,"",MonthlyFAME!F418) -> 10655 | F416: =IF(MonthlyFAME!G418=0,"",MonthlyFAME!G418) -> 11465 | G416: =IF(MonthlyFAME!H418=0,"",MonthlyFAME!H418) -> 9.8121899 | H416: =IF(MonthlyFAME!I418=0,"",MonthlyFAME!I418) -> 25451 | I416: =IF(MonthlyFAME!J418=0,"",MonthlyFAME!J418) -> 842.1 | K416: =IF(MonthlyFAME!L418=0,"",MonthlyFAME!L418) -> 240.69583 | L416: =IF(MonthlyFAME!M418=0,"",MonthlyFAME!M418) -> 2676.3 | M416: =IF(MonthlyFAME!N418=0,"",MonthlyFAME!N418) | N416: =IF(MonthlyFAME!O418=0,"",MonthlyFAME!O418) | O416: =IF(MonthlyFAME!P418=0,"",MonthlyFAME!P418) | P416: =IF(MonthlyFAME!Q418=0,"",MonthlyFAME!Q418) | Q416: =IF(MonthlyFAME!R418=0,"",MonthlyFAME!R418) | R416: =IF(MonthlyFAME!S418=0,"",MonthlyFAME!S418) | ... T416: =IF(MonthlyFAME!U418=0,"",MonthlyFAME!U418) -> 15.095238
A417: =IF(MonthlyFAME!A419=0,"",MonthlyFAME!A419) -> 34485 | B417: =IF(MonthlyFAME!B419=0,"",MonthlyFAME!B419) | C417: =IF(MonthlyFAME!C419=0,"",MonthlyFAME!C419) -> 78.8 | E417: =IF(MonthlyFAME!F419=0,"",MonthlyFAME!F419) -> 10468 | F417: =IF(MonthlyFAME!G419=0,"",MonthlyFAME!G419) -> 11690 | G417: =IF(MonthlyFAME!H419=0,"",MonthlyFAME!H419) -> 9.7500443 | H417: =IF(MonthlyFAME!I419=0,"",MonthlyFAME!I419) -> 25455 | I417: =IF(MonthlyFAME!J419=0,"",MonthlyFAME!J419) -> 840.4 | K417: =IF(MonthlyFAME!L419=0,"",MonthlyFAME!L419) -> 243.25943 | L417: =IF(MonthlyFAME!M419=0,"",MonthlyFAME!M419) -> 2652.6 | M417: =IF(MonthlyFAME!N419=0,"",MonthlyFAME!N419) | N417: =IF(MonthlyFAME!O419=0,"",MonthlyFAME!O419) | O417: =IF(MonthlyFAME!P419=0,"",MonthlyFAME!P419) | P417: =IF(MonthlyFAME!Q419=0,"",MonthlyFAME!Q419) | Q417: =IF(MonthlyFAME!R419=0,"",MonthlyFAME!R419) | R417: =IF(MonthlyFAME!S419=0,"",MonthlyFAME!S419) | ... T417: =IF(MonthlyFAME!U419=0,"",MonthlyFAME!U419) -> 16.204545
A418: =IF(MonthlyFAME!A420=0,"",MonthlyFAME!A420) -> 34515 | B418: =IF(MonthlyFAME!B420=0,"",MonthlyFAME!B420) | C418: =IF(MonthlyFAME!C420=0,"",MonthlyFAME!C420) -> 77.9 | E418: =IF(MonthlyFAME!F420=0,"",MonthlyFAME!F420) -> 11118 | F418: =IF(MonthlyFAME!G420=0,"",MonthlyFAME!G420) -> 11560 | G418: =IF(MonthlyFAME!H420=0,"",MonthlyFAME!H420) -> 9.7066023 | H418: =IF(MonthlyFAME!I420=0,"",MonthlyFAME!I420) -> 25451 | I418: =IF(MonthlyFAME!J420=0,"",MonthlyFAME!J420) -> 839.2 | K418: =IF(MonthlyFAME!L420=0,"",MonthlyFAME!L420) -> 243.94549 | L418: =IF(MonthlyFAME!M420=0,"",MonthlyFAME!M420) -> 2624.9 | M418: =IF(MonthlyFAME!N420=0,"",MonthlyFAME!N420) | N418: =IF(MonthlyFAME!O420=0,"",MonthlyFAME!O420) | O418: =IF(MonthlyFAME!P420=0,"",MonthlyFAME!P420) | P418: =IF(MonthlyFAME!Q420=0,"",MonthlyFAME!Q420) | Q418: =IF(MonthlyFAME!R420=0,"",MonthlyFAME!R420) | R418: =IF(MonthlyFAME!S420=0,"",MonthlyFAME!S420) | ... T418: =IF(MonthlyFAME!U420=0,"",MonthlyFAME!U420) -> 16.782727
A419: =IF(MonthlyFAME!A421=0,"",MonthlyFAME!A421) -> 34546 | B419: =IF(MonthlyFAME!B421=0,"",MonthlyFAME!B421) | C419: =IF(MonthlyFAME!C421=0,"",MonthlyFAME!C421) -> 78.3 | E419: =IF(MonthlyFAME!F421=0,"",MonthlyFAME!F421) -> 10652 | F419: =IF(MonthlyFAME!G421=0,"",MonthlyFAME!G421) -> 11514 | G419: =IF(MonthlyFAME!H421=0,"",MonthlyFAME!H421) -> 9.5850608 | H419: =IF(MonthlyFAME!I421=0,"",MonthlyFAME!I421) -> 25516 | I419: =IF(MonthlyFAME!J421=0,"",MonthlyFAME!J421) -> 841.1 | K419: =IF(MonthlyFAME!L421=0,"",MonthlyFAME!L421) -> 244.77739 | L419: =IF(MonthlyFAME!M421=0,"",MonthlyFAME!M421) -> 2593.5 | M419: =IF(MonthlyFAME!N421=0,"",MonthlyFAME!N421) | N419: =IF(MonthlyFAME!O421=0,"",MonthlyFAME!O421) | O419: =IF(MonthlyFAME!P421=0,"",MonthlyFAME!P421) | P419: =IF(MonthlyFAME!Q421=0,"",MonthlyFAME!Q421) | Q419: =IF(MonthlyFAME!R421=0,"",MonthlyFAME!R421) | R419: =IF(MonthlyFAME!S421=0,"",MonthlyFAME!S421) | ... T419: =IF(MonthlyFAME!U421=0,"",MonthlyFAME!U421) -> 17.604762
A420: =IF(MonthlyFAME!A422=0,"",MonthlyFAME!A422) -> 34577 | B420: =IF(MonthlyFAME!B422=0,"",MonthlyFAME!B422) | C420: =IF(MonthlyFAME!C422=0,"",MonthlyFAME!C422) -> 78.6 | E420: =IF(MonthlyFAME!F422=0,"",MonthlyFAME!F422) -> 11152 | F420: =IF(MonthlyFAME!G422=0,"",MonthlyFAME!G422) -> 11317 | G420: =IF(MonthlyFAME!H422=0,"",MonthlyFAME!H422) -> 9.5398469 | H420: =IF(MonthlyFAME!I422=0,"",MonthlyFAME!I422) -> 25517 | I420: =IF(MonthlyFAME!J422=0,"",MonthlyFAME!J422) -> 843.9 | K420: =IF(MonthlyFAME!L422=0,"",MonthlyFAME!L422) -> 245.57077 | L420: =IF(MonthlyFAME!M422=0,"",MonthlyFAME!M422) -> 2553.2 | M420: =IF(MonthlyFAME!N422=0,"",MonthlyFAME!N422) | N420: =IF(MonthlyFAME!O422=0,"",MonthlyFAME!O422) | O420: =IF(MonthlyFAME!P422=0,"",MonthlyFAME!P422) | P420: =IF(MonthlyFAME!Q422=0,"",MonthlyFAME!Q422) | Q420: =IF(MonthlyFAME!R422=0,"",MonthlyFAME!R422) | R420: =IF(MonthlyFAME!S422=0,"",MonthlyFAME!S422) | ... T420: =IF(MonthlyFAME!U422=0,"",MonthlyFAME!U422) -> 16.727826
A421: =IF(MonthlyFAME!A423=0,"",MonthlyFAME!A423) -> 34607 | B421: =IF(MonthlyFAME!B423=0,"",MonthlyFAME!B423) | C421: =IF(MonthlyFAME!C423=0,"",MonthlyFAME!C423) -> 79.3 | E421: =IF(MonthlyFAME!F423=0,"",MonthlyFAME!F423) -> 11026 | F421: =IF(MonthlyFAME!G423=0,"",MonthlyFAME!G423) -> 11575 | G421: =IF(MonthlyFAME!H423=0,"",MonthlyFAME!H423) -> 9.3588198 | H421: =IF(MonthlyFAME!I423=0,"",MonthlyFAME!I423) -> 25559 | I421: =IF(MonthlyFAME!J423=0,"",MonthlyFAME!J423) -> 846.3 | K421: =IF(MonthlyFAME!L423=0,"",MonthlyFAME!L423) -> 245.77298 | L421: =IF(MonthlyFAME!M423=0,"",MonthlyFAME!M423) -> 2524.5 | M421: =IF(MonthlyFAME!N423=0,"",MonthlyFAME!N423) | N421: =IF(MonthlyFAME!O423=0,"",MonthlyFAME!O423) | O421: =IF(MonthlyFAME!P423=0,"",MonthlyFAME!P423) | P421: =IF(MonthlyFAME!Q423=0,"",MonthlyFAME!Q423) | Q421: =IF(MonthlyFAME!R423=0,"",MonthlyFAME!R423) | R421: =IF(MonthlyFAME!S423=0,"",MonthlyFAME!S423) | ... T421: =IF(MonthlyFAME!U423=0,"",MonthlyFAME!U423) -> 15.83
A422: =IF(MonthlyFAME!A424=0,"",MonthlyFAME!A424) -> 34638 | B422: =IF(MonthlyFAME!B424=0,"",MonthlyFAME!B424) | C422: =IF(MonthlyFAME!C424=0,"",MonthlyFAME!C424) -> 79.5 | E422: =IF(MonthlyFAME!F424=0,"",MonthlyFAME!F424) -> 11143 | F422: =IF(MonthlyFAME!G424=0,"",MonthlyFAME!G424) -> 11749 | G422: =IF(MonthlyFAME!H424=0,"",MonthlyFAME!H424) -> 9.2584046 | H422: =IF(MonthlyFAME!I424=0,"",MonthlyFAME!I424) -> 25561 | I422: =IF(MonthlyFAME!J424=0,"",MonthlyFAME!J424) -> 846.4 | K422: =IF(MonthlyFAME!L424=0,"",MonthlyFAME!L424) -> 247.28118 | L422: =IF(MonthlyFAME!M424=0,"",MonthlyFAME!M424) -> 2484.9 | M422: =IF(MonthlyFAME!N424=0,"",MonthlyFAME!N424) | N422: =IF(MonthlyFAME!O424=0,"",MonthlyFAME!O424) | O422: =IF(MonthlyFAME!P424=0,"",MonthlyFAME!P424) | P422: =IF(MonthlyFAME!Q424=0,"",MonthlyFAME!Q424) | Q422: =IF(MonthlyFAME!R424=0,"",MonthlyFAME!R424) | R422: =IF(MonthlyFAME!S424=0,"",MonthlyFAME!S424) | ... T422: =IF(MonthlyFAME!U424=0,"",MonthlyFAME!U424) -> 16.457143
A423: =IF(MonthlyFAME!A425=0,"",MonthlyFAME!A425) -> 34668 | B423: =IF(MonthlyFAME!B425=0,"",MonthlyFAME!B425) | C423: =IF(MonthlyFAME!C425=0,"",MonthlyFAME!C425) -> 79.4 | E423: =IF(MonthlyFAME!F425=0,"",MonthlyFAME!F425) -> 11788 | F423: =IF(MonthlyFAME!G425=0,"",MonthlyFAME!G425) -> 12016 | G423: =IF(MonthlyFAME!H425=0,"",MonthlyFAME!H425) -> 9.079929 | H423: =IF(MonthlyFAME!I425=0,"",MonthlyFAME!I425) -> 25594 | I423: =IF(MonthlyFAME!J425=0,"",MonthlyFAME!J425) -> 847.1 | K423: =IF(MonthlyFAME!L425=0,"",MonthlyFAME!L425) -> 247.67618 | L423: =IF(MonthlyFAME!M425=0,"",MonthlyFAME!M425) -> 2453.5 | M423: =IF(MonthlyFAME!N425=0,"",MonthlyFAME!N425) | N423: =IF(MonthlyFAME!O425=0,"",MonthlyFAME!O425) | O423: =IF(MonthlyFAME!P425=0,"",MonthlyFAME!P425) | P423: =IF(MonthlyFAME!Q425=0,"",MonthlyFAME!Q425) | Q423: =IF(MonthlyFAME!R425=0,"",MonthlyFAME!R425) | R423: =IF(MonthlyFAME!S425=0,"",MonthlyFAME!S425) | ... T423: =IF(MonthlyFAME!U425=0,"",MonthlyFAME!U425) -> 17.217273
A424: =IF(MonthlyFAME!A426=0,"",MonthlyFAME!A426) -> 34699 | B424: =IF(MonthlyFAME!B426=0,"",MonthlyFAME!B426) | C424: =IF(MonthlyFAME!C426=0,"",MonthlyFAME!C426) -> 80.2 | E424: =IF(MonthlyFAME!F426=0,"",MonthlyFAME!F426) -> 11272 | F424: =IF(MonthlyFAME!G426=0,"",MonthlyFAME!G426) -> 12228 | G424: =IF(MonthlyFAME!H426=0,"",MonthlyFAME!H426) -> 8.9648306 | H424: =IF(MonthlyFAME!I426=0,"",MonthlyFAME!I426) -> 25600 | I424: =IF(MonthlyFAME!J426=0,"",MonthlyFAME!J426) -> 853 | K424: =IF(MonthlyFAME!L426=0,"",MonthlyFAME!L426) -> 249.1837 | L424: =IF(MonthlyFAME!M426=0,"",MonthlyFAME!M426) -> 2407.4 | M424: =IF(MonthlyFAME!N426=0,"",MonthlyFAME!N426) | N424: =IF(MonthlyFAME!O426=0,"",MonthlyFAME!O426) | O424: =IF(MonthlyFAME!P426=0,"",MonthlyFAME!P426) | P424: =IF(MonthlyFAME!Q426=0,"",MonthlyFAME!Q426) | Q424: =IF(MonthlyFAME!R426=0,"",MonthlyFAME!R426) | R424: =IF(MonthlyFAME!S426=0,"",MonthlyFAME!S426) | ... T424: =IF(MonthlyFAME!U426=0,"",MonthlyFAME!U426) -> 15.855455
A425: =IF(MonthlyFAME!A427=0,"",MonthlyFAME!A427) -> 34730 | B425: =IF(MonthlyFAME!B427=0,"",MonthlyFAME!B427) | C425: =IF(MonthlyFAME!C427=0,"",MonthlyFAME!C427) -> 78.8 | E425: =IF(MonthlyFAME!F427=0,"",MonthlyFAME!F427) -> 11589 | F425: =IF(MonthlyFAME!G427=0,"",MonthlyFAME!G427) -> 11737 | G425: =IF(MonthlyFAME!H427=0,"",MonthlyFAME!H427) -> 8.8924501 | H425: =IF(MonthlyFAME!I427=0,"",MonthlyFAME!I427) -> 25583 | I425: =IF(MonthlyFAME!J427=0,"",MonthlyFAME!J427) -> 854.5 | K425: =IF(MonthlyFAME!L427=0,"",MonthlyFAME!L427) -> 249.23629 | L425: =IF(MonthlyFAME!M427=0,"",MonthlyFAME!M427) -> 2387.3 | M425: =IF(MonthlyFAME!N427=0,"",MonthlyFAME!N427) | N425: =IF(MonthlyFAME!O427=0,"",MonthlyFAME!O427) | O425: =IF(MonthlyFAME!P427=0,"",MonthlyFAME!P427) | P425: =IF(MonthlyFAME!Q427=0,"",MonthlyFAME!Q427) | Q425: =IF(MonthlyFAME!R427=0,"",MonthlyFAME!R427) | R425: =IF(MonthlyFAME!S427=0,"",MonthlyFAME!S427) | ... T425: =IF(MonthlyFAME!U427=0,"",MonthlyFAME!U427) -> 16.569545
A426: =IF(MonthlyFAME!A428=0,"",MonthlyFAME!A428) -> 34758 | B426: =IF(MonthlyFAME!B428=0,"",MonthlyFAME!B428) | C426: =IF(MonthlyFAME!C428=0,"",MonthlyFAME!C428) -> 78.9 | E426: =IF(MonthlyFAME!F428=0,"",MonthlyFAME!F428) -> 11657 | F426: =IF(MonthlyFAME!G428=0,"",MonthlyFAME!G428) -> 11794 | G426: =IF(MonthlyFAME!H428=0,"",MonthlyFAME!H428) -> 8.8718277 | H426: =IF(MonthlyFAME!I428=0,"",MonthlyFAME!I428) -> 25638 | I426: =IF(MonthlyFAME!J428=0,"",MonthlyFAME!J428) -> 853.5 | K426: =IF(MonthlyFAME!L428=0,"",MonthlyFAME!L428) -> 250.12922 | L426: =IF(MonthlyFAME!M428=0,"",MonthlyFAME!M428) -> 2358.6 | M426: =IF(MonthlyFAME!N428=0,"",MonthlyFAME!N428) | N426: =IF(MonthlyFAME!O428=0,"",MonthlyFAME!O428) | O426: =IF(MonthlyFAME!P428=0,"",MonthlyFAME!P428) | P426: =IF(MonthlyFAME!Q428=0,"",MonthlyFAME!Q428) | Q426: =IF(MonthlyFAME!R428=0,"",MonthlyFAME!R428) | R426: =IF(MonthlyFAME!S428=0,"",MonthlyFAME!S428) | ... T426: =IF(MonthlyFAME!U428=0,"",MonthlyFAME!U428) -> 17.1025
A427: =IF(MonthlyFAME!A429=0,"",MonthlyFAME!A429) -> 34789 | B427: =IF(MonthlyFAME!B429=0,"",MonthlyFAME!B429) | C427: =IF(MonthlyFAME!C429=0,"",MonthlyFAME!C429) -> 79.2 | E427: =IF(MonthlyFAME!F429=0,"",MonthlyFAME!F429) -> 12032 | F427: =IF(MonthlyFAME!G429=0,"",MonthlyFAME!G429) -> 12036 | G427: =IF(MonthlyFAME!H429=0,"",MonthlyFAME!H429) -> 8.8649838 | H427: =IF(MonthlyFAME!I429=0,"",MonthlyFAME!I429) -> 25670 | I427: =IF(MonthlyFAME!J429=0,"",MonthlyFAME!J429) -> 852.4 | K427: =IF(MonthlyFAME!L429=0,"",MonthlyFAME!L429) -> 250.99827 | L427: =IF(MonthlyFAME!M429=0,"",MonthlyFAME!M429) -> 2341.9 | M427: =IF(MonthlyFAME!N429=0,"",MonthlyFAME!N429) | N427: =IF(MonthlyFAME!O429=0,"",MonthlyFAME!O429) | O427: =IF(MonthlyFAME!P429=0,"",MonthlyFAME!P429) | P427: =IF(MonthlyFAME!Q429=0,"",MonthlyFAME!Q429) | Q427: =IF(MonthlyFAME!R429=0,"",MonthlyFAME!R429) | R427: =IF(MonthlyFAME!S429=0,"",MonthlyFAME!S429) | ... T427: =IF(MonthlyFAME!U429=0,"",MonthlyFAME!U429) -> 17.002609
... A448: =IF(MonthlyFAME!A450=0,"",MonthlyFAME!A450) -> 35430 | B448: =IF(MonthlyFAME!B450=0,"",MonthlyFAME!B450) | C448: =IF(MonthlyFAME!C450=0,"",MonthlyFAME!C450) -> 81.8 | E448: =IF(MonthlyFAME!F450=0,"",MonthlyFAME!F450) -> 12970 | F448: =IF(MonthlyFAME!G450=0,"",MonthlyFAME!G450) -> 13792 | G448: =IF(MonthlyFAME!H450=0,"",MonthlyFAME!H450) -> 7.8411369 | H448: =IF(MonthlyFAME!I450=0,"",MonthlyFAME!I450) -> 26198 | I448: =IF(MonthlyFAME!J450=0,"",MonthlyFAME!J450) -> 866.1 | K448: =IF(MonthlyFAME!L450=0,"",MonthlyFAME!L450) -> 267.10557 | L448: =IF(MonthlyFAME!M450=0,"",MonthlyFAME!M450) -> 1872.1 | M448: =IF(MonthlyFAME!N450=0,"",MonthlyFAME!N450) | N448: =IF(MonthlyFAME!O450=0,"",MonthlyFAME!O450) | O448: =IF(MonthlyFAME!P450=0,"",MonthlyFAME!P450) | P448: =IF(MonthlyFAME!Q450=0,"",MonthlyFAME!Q450) | Q448: =IF(MonthlyFAME!R450=0,"",MonthlyFAME!R450) | R448: =IF(MonthlyFAME!S450=0,"",MonthlyFAME!S450) | ... T448: =IF(MonthlyFAME!U450=0,"",MonthlyFAME!U450) -> 23.823182
A449: =IF(MonthlyFAME!A451=0,"",MonthlyFAME!A451) -> 35461 | B449: =IF(MonthlyFAME!B451=0,"",MonthlyFAME!B451) -> 63.3 | C449: =IF(MonthlyFAME!C451=0,"",MonthlyFAME!C451) -> 81.8 | D449: =IF(MonthlyFAME!D451=0,"",MonthlyFAME!D451) -> 58.9698 | E449: =IF(MonthlyFAME!F451=0,"",MonthlyFAME!F451) -> 19558 | F449: =IF(MonthlyFAME!G451=0,"",MonthlyFAME!G451) -> 17288 | G449: =IF(MonthlyFAME!H451=0,"",MonthlyFAME!H451) -> 7.669046 | H449: =IF(MonthlyFAME!I451=0,"",MonthlyFAME!I451) -> 26258 | I449: =IF(MonthlyFAME!J451=0,"",MonthlyFAME!J451) -> 867.8 | J449: 466.63636 | K449: =IF(MonthlyFAME!L451=0,"",MonthlyFAME!L451) -> 267.57221 | L449: =IF(MonthlyFAME!M451=0,"",MonthlyFAME!M451) -> 1818.4 | M449: =IF(MonthlyFAME!N451=0,"",MonthlyFAME!N451) | N449: =IF(MonthlyFAME!O451=0,"",MonthlyFAME!O451) | O449: =IF(MonthlyFAME!P451=0,"",MonthlyFAME!P451) | P449: =IF(MonthlyFAME!Q451=0,"",MonthlyFAME!Q451) | Q449: =IF(MonthlyFAME!R451=0,"",MonthlyFAME!R451) | R449: =IF(MonthlyFAME!S451=0,"",MonthlyFAME!S451) | ... T449: =IF(MonthlyFAME!U451=0,"",MonthlyFAME!U451) -> 23.472609
A450: =IF(MonthlyFAME!A452=0,"",MonthlyFAME!A452) -> 35489 | B450: =IF(MonthlyFAME!B452=0,"",MonthlyFAME!B452) -> 64 | C450: =IF(MonthlyFAME!C452=0,"",MonthlyFAME!C452) -> 82.1 | D450: =IF(MonthlyFAME!D452=0,"",MonthlyFAME!D452) -> 59.7182 | E450: =IF(MonthlyFAME!F452=0,"",MonthlyFAME!F452) -> 19053 | F450: =IF(MonthlyFAME!G452=0,"",MonthlyFAME!G452) -> 17107 | G450: =IF(MonthlyFAME!H452=0,"",MonthlyFAME!H452) -> 7.4890177 | H450: =IF(MonthlyFAME!I452=0,"",MonthlyFAME!I452) -> 26324 | I450: =IF(MonthlyFAME!J452=0,"",MonthlyFAME!J452) -> 870.2 | J450: 479.11515 | K450: =IF(MonthlyFAME!L452=0,"",MonthlyFAME!L452) -> 267.76415 | L450: =IF(MonthlyFAME!M452=0,"",MonthlyFAME!M452) -> 1752.8 | M450: =IF(MonthlyFAME!N452=0,"",MonthlyFAME!N452) | N450: =IF(MonthlyFAME!O452=0,"",MonthlyFAME!O452) | O450: =IF(MonthlyFAME!P452=0,"",MonthlyFAME!P452) | P450: =IF(MonthlyFAME!Q452=0,"",MonthlyFAME!Q452) | Q450: =IF(MonthlyFAME!R452=0,"",MonthlyFAME!R452) | R450: =IF(MonthlyFAME!S452=0,"",MonthlyFAME!S452) | ... T450: =IF(MonthlyFAME!U452=0,"",MonthlyFAME!U452) -> 20.827
A451: =IF(MonthlyFAME!A453=0,"",MonthlyFAME!A453) -> 35520 | B451: =IF(MonthlyFAME!B453=0,"",MonthlyFAME!B453) -> 64 | C451: =IF(MonthlyFAME!C453=0,"",MonthlyFAME!C453) -> 80.9 | D451: =IF(MonthlyFAME!D453=0,"",MonthlyFAME!D453) -> 59.97 | E451: =IF(MonthlyFAME!F453=0,"",MonthlyFAME!F453) -> 18509 | F451: =IF(MonthlyFAME!G453=0,"",MonthlyFAME!G453) -> 17733 | G451: =IF(MonthlyFAME!H453=0,"",MonthlyFAME!H453) -> 7.3245275 | H451: =IF(MonthlyFAME!I453=0,"",MonthlyFAME!I453) -> 26381 | I451: =IF(MonthlyFAME!J453=0,"",MonthlyFAME!J453) -> 873.7 | J451: 490.71515 | K451: =IF(MonthlyFAME!L453=0,"",MonthlyFAME!L453) -> 271.21285 | L451: =IF(MonthlyFAME!M453=0,"",MonthlyFAME!M453) -> 1704.3 | M451: =IF(MonthlyFAME!N453=0,"",MonthlyFAME!N453) | N451: =IF(MonthlyFAME!O453=0,"",MonthlyFAME!O453) | O451: =IF(MonthlyFAME!P453=0,"",MonthlyFAME!P453) | P451: =IF(MonthlyFAME!Q453=0,"",MonthlyFAME!Q453) | Q451: =IF(MonthlyFAME!R453=0,"",MonthlyFAME!R453) | R451: =IF(MonthlyFAME!S453=0,"",MonthlyFAME!S453) | ... T451: =IF(MonthlyFAME!U453=0,"",MonthlyFAME!U453) -> 19.055238
A452: =IF(MonthlyFAME!A454=0,"",MonthlyFAME!A454) -> 35550 | B452: =IF(MonthlyFAME!B454=0,"",MonthlyFAME!B454) -> 64.6 | C452: =IF(MonthlyFAME!C454=0,"",MonthlyFAME!C454) -> 82.9 | D452: =IF(MonthlyFAME!D454=0,"",MonthlyFAME!D454) -> 60.1678 | E452: =IF(MonthlyFAME!F454=0,"",MonthlyFAME!F454) -> 19942 | F452: =IF(MonthlyFAME!G454=0,"",MonthlyFAME!G454) -> 18571 | G452: =IF(MonthlyFAME!H454=0,"",MonthlyFAME!H454) -> 7.2050562 | H452: =IF(MonthlyFAME!I454=0,"",MonthlyFAME!I454) -> 26428 | I452: =IF(MonthlyFAME!J454=0,"",MonthlyFAME!J454) -> 877.5 | J452: 491.41818 | K452: =IF(MonthlyFAME!L454=0,"",MonthlyFAME!L454) -> 269.59258 | L452: =IF(MonthlyFAME!M454=0,"",MonthlyFAME!M454) -> 1662.6 | M452: =IF(MonthlyFAME!N454=0,"",MonthlyFAME!N454) | N452: =IF(MonthlyFAME!O454=0,"",MonthlyFAME!O454) | O452: =IF(MonthlyFAME!P454=0,"",MonthlyFAME!P454) | P452: =IF(MonthlyFAME!Q454=0,"",MonthlyFAME!Q454) | Q452: =IF(MonthlyFAME!R454=0,"",MonthlyFAME!R454) | R452: =IF(MonthlyFAME!S454=0,"",MonthlyFAME!S454) | ... T452: =IF(MonthlyFAME!U454=0,"",MonthlyFAME!U454) -> 17.481818
A453: =IF(MonthlyFAME!A455=0,"",MonthlyFAME!A455) -> 35581 | B453: =IF(MonthlyFAME!B455=0,"",MonthlyFAME!B455) -> 64.1 | C453: =IF(MonthlyFAME!C455=0,"",MonthlyFAME!C455) -> 82.6 | D453: =IF(MonthlyFAME!D455=0,"",MonthlyFAME!D455) -> 59.5863 | E453: =IF(MonthlyFAME!F455=0,"",MonthlyFAME!F455) -> 19180 | F453: =IF(MonthlyFAME!G455=0,"",MonthlyFAME!G455) -> 17946 | G453: =IF(MonthlyFAME!H455=0,"",MonthlyFAME!H455) -> 7.1832123 | H453: =IF(MonthlyFAME!I455=0,"",MonthlyFAME!I455) -> 26450 | I453: =IF(MonthlyFAME!J455=0,"",MonthlyFAME!J455) -> 878.1 | J453: 491.06667 | K453: =IF(MonthlyFAME!L455=0,"",MonthlyFAME!L455) -> 270.53525 | L453: =IF(MonthlyFAME!M455=0,"",MonthlyFAME!M455) -> 1619.6 | M453: =IF(MonthlyFAME!N455=0,"",MonthlyFAME!N455) | N453: =IF(MonthlyFAME!O455=0,"",MonthlyFAME!O455) | O453: =IF(MonthlyFAME!P455=0,"",MonthlyFAME!P455) | P453: =IF(MonthlyFAME!Q455=0,"",MonthlyFAME!Q455) | Q453: =IF(MonthlyFAME!R455=0,"",MonthlyFAME!R455) | R453: =IF(MonthlyFAME!S455=0,"",MonthlyFAME!S455) | ... T453: =IF(MonthlyFAME!U455=0,"",MonthlyFAME!U455) -> 19.127273
A454: =IF(MonthlyFAME!A456=0,"",MonthlyFAME!A456) -> 35611 | B454: =IF(MonthlyFAME!B456=0,"",MonthlyFAME!B456) -> 64.5 | C454: =IF(MonthlyFAME!C456=0,"",MonthlyFAME!C456) -> 82.8 | D454: =IF(MonthlyFAME!D456=0,"",MonthlyFAME!D456) -> 59.9621 | E454: =IF(MonthlyFAME!F456=0,"",MonthlyFAME!F456) -> 18731 | F454: =IF(MonthlyFAME!G456=0,"",MonthlyFAME!G456) -> 18573 | G454: =IF(MonthlyFAME!H456=0,"",MonthlyFAME!H456) -> 7.1801155 | H454: =IF(MonthlyFAME!I456=0,"",MonthlyFAME!I456) -> 26514 | I454: =IF(MonthlyFAME!J456=0,"",MonthlyFAME!J456) -> 878.3 | J454: 487.37576 | K454: =IF(MonthlyFAME!L456=0,"",MonthlyFAME!L456) -> 270.91307 | L454: =IF(MonthlyFAME!M456=0,"",MonthlyFAME!M456) -> 1571.5 | M454: =IF(MonthlyFAME!N456=0,"",MonthlyFAME!N456) | N454: =IF(MonthlyFAME!O456=0,"",MonthlyFAME!O456) | O454: =IF(MonthlyFAME!P456=0,"",MonthlyFAME!P456) | P454: =IF(MonthlyFAME!Q456=0,"",MonthlyFAME!Q456) | Q454: =IF(MonthlyFAME!R456=0,"",MonthlyFAME!R456) | R454: =IF(MonthlyFAME!S456=0,"",MonthlyFAME!S456) | ... T454: =IF(MonthlyFAME!U456=0,"",MonthlyFAME!U456) -> 17.589524
A455: =IF(MonthlyFAME!A457=0,"",MonthlyFAME!A457) -> 35642 | B455: =IF(MonthlyFAME!B457=0,"",MonthlyFAME!B457) -> 64.8 | C455: =IF(MonthlyFAME!C457=0,"",MonthlyFAME!C457) -> 84.5 | D455: =IF(MonthlyFAME!D457=0,"",MonthlyFAME!D457) -> 60.0228 | E455: =IF(MonthlyFAME!F457=0,"",MonthlyFAME!F457) -> 19197 | F455: =IF(MonthlyFAME!G457=0,"",MonthlyFAME!G457) -> 18464 | G455: =IF(MonthlyFAME!H457=0,"",MonthlyFAME!H457) -> 7.2893337 | H455: =IF(MonthlyFAME!I457=0,"",MonthlyFAME!I457) -> 26493 | I455: =IF(MonthlyFAME!J457=0,"",MonthlyFAME!J457) -> 877 | J455: 498.97576 | K455: =IF(MonthlyFAME!L457=0,"",MonthlyFAME!L457) -> 272.78631 | L455: =IF(MonthlyFAME!M457=0,"",MonthlyFAME!M457) -> 1554.1 | M455: =IF(MonthlyFAME!N457=0,"",MonthlyFAME!N457) | N455: =IF(MonthlyFAME!O457=0,"",MonthlyFAME!O457) | O455: =IF(MonthlyFAME!P457=0,"",MonthlyFAME!P457) | P455: =IF(MonthlyFAME!Q457=0,"",MonthlyFAME!Q457) | Q455: =IF(MonthlyFAME!R457=0,"",MonthlyFAME!R457) | R455: =IF(MonthlyFAME!S457=0,"",MonthlyFAME!S457) | ... T455: =IF(MonthlyFAME!U457=0,"",MonthlyFAME!U457) -> 18.503913
A456: =IF(MonthlyFAME!A458=0,"",MonthlyFAME!A458) -> 35673 | B456: =IF(MonthlyFAME!B458=0,"",MonthlyFAME!B458) -> 64.9 | C456: =IF(MonthlyFAME!C458=0,"",MonthlyFAME!C458) -> 83.5 | D456: =IF(MonthlyFAME!D458=0,"",MonthlyFAME!D458) -> 60.3402 | E456: =IF(MonthlyFAME!F458=0,"",MonthlyFAME!F458) -> 18364 | F456: =IF(MonthlyFAME!G458=0,"",MonthlyFAME!G458) -> 17051 | G456: =IF(MonthlyFAME!H458=0,"",MonthlyFAME!H458) -> 7.0870281 | H456: =IF(MonthlyFAME!I458=0,"",MonthlyFAME!I458) -> 26509 | I456: =IF(MonthlyFAME!J458=0,"",MonthlyFAME!J458) -> 877.9 | J456: 506.18182 | K456: =IF(MonthlyFAME!L458=0,"",MonthlyFAME!L458) -> 274.44992 | L456: =IF(MonthlyFAME!M458=0,"",MonthlyFAME!M458) -> 1526.5 | M456: =IF(MonthlyFAME!N458=0,"",MonthlyFAME!N458) | N456: =IF(MonthlyFAME!O458=0,"",MonthlyFAME!O458) | O456: =IF(MonthlyFAME!P458=0,"",MonthlyFAME!P458) | P456: =IF(MonthlyFAME!Q458=0,"",MonthlyFAME!Q458) | Q456: =IF(MonthlyFAME!R458=0,"",MonthlyFAME!R458) | R456: =IF(MonthlyFAME!S458=0,"",MonthlyFAME!S458) | ... T456: =IF(MonthlyFAME!U458=0,"",MonthlyFAME!U458) -> 18.639048
A457: =IF(MonthlyFAME!A459=0,"",MonthlyFAME!A459) -> 35703 | B457: =IF(MonthlyFAME!B459=0,"",MonthlyFAME!B459) -> 65 | C457: =IF(MonthlyFAME!C459=0,"",MonthlyFAME!C459) -> 84 | D457: =IF(MonthlyFAME!D459=0,"",MonthlyFAME!D459) -> 60.3826 | E457: =IF(MonthlyFAME!F459=0,"",MonthlyFAME!F459) -> 19128 | F457: =IF(MonthlyFAME!G459=0,"",MonthlyFAME!G459) -> 17769 | G457: =IF(MonthlyFAME!H459=0,"",MonthlyFAME!H459) -> 6.840094 | H457: =IF(MonthlyFAME!I459=0,"",MonthlyFAME!I459) -> 26572 | I457: =IF(MonthlyFAME!J459=0,"",MonthlyFAME!J459) -> 880.2 | J457: 518.83636 | K457: =IF(MonthlyFAME!L459=0,"",MonthlyFAME!L459) -> 275.77948 | L457: =IF(MonthlyFAME!M459=0,"",MonthlyFAME!M459) -> 1497.8 | M457: =IF(MonthlyFAME!N459=0,"",MonthlyFAME!N459) | N457: =IF(MonthlyFAME!O459=0,"",MonthlyFAME!O459) | O457: =IF(MonthlyFAME!P459=0,"",MonthlyFAME!P459) | P457: =IF(MonthlyFAME!Q459=0,"",MonthlyFAME!Q459) | Q457: =IF(MonthlyFAME!R459=0,"",MonthlyFAME!R459) | R457: =IF(MonthlyFAME!S459=0,"",MonthlyFAME!S459) | ... T457: =IF(MonthlyFAME!U459=0,"",MonthlyFAME!U459) -> 18.476818
A458: =IF(MonthlyFAME!A460=0,"",MonthlyFAME!A460) -> 35734 | B458: =IF(MonthlyFAME!B460=0,"",MonthlyFAME!B460) -> 65.4 | C458: =IF(MonthlyFAME!C460=0,"",MonthlyFAME!C460) -> 85 | D458: =IF(MonthlyFAME!D460=0,"",MonthlyFAME!D460) -> 60.6386 | E458: =IF(MonthlyFAME!F460=0,"",MonthlyFAME!F460) -> 19429 | F458: =IF(MonthlyFAME!G460=0,"",MonthlyFAME!G460) -> 18478 | G458: =IF(MonthlyFAME!H460=0,"",MonthlyFAME!H460) -> 6.6954265 | H458: =IF(MonthlyFAME!I460=0,"",MonthlyFAME!I460) -> 26603 | I458: =IF(MonthlyFAME!J460=0,"",MonthlyFAME!J460) -> 882.9 | J458: 522.35152 | K458: =IF(MonthlyFAME!L460=0,"",MonthlyFAME!L460) -> 276.63451 | L458: =IF(MonthlyFAME!M460=0,"",MonthlyFAME!M460) -> 1464.1 | M458: =IF(MonthlyFAME!N460=0,"",MonthlyFAME!N460) | N458: =IF(MonthlyFAME!O460=0,"",MonthlyFAME!O460) | O458: =IF(MonthlyFAME!P460=0,"",MonthlyFAME!P460) | P458: =IF(MonthlyFAME!Q460=0,"",MonthlyFAME!Q460) | Q458: =IF(MonthlyFAME!R460=0,"",MonthlyFAME!R460) | R458: =IF(MonthlyFAME!S460=0,"",MonthlyFAME!S460) | ... T458: =IF(MonthlyFAME!U460=0,"",MonthlyFAME!U460) -> 19.906957
A459: =IF(MonthlyFAME!A461=0,"",MonthlyFAME!A461) -> 35764 | B459: =IF(MonthlyFAME!B461=0,"",MonthlyFAME!B461) -> 65.7 | C459: =IF(MonthlyFAME!C461=0,"",MonthlyFAME!C461) -> 85.1 | D459: =IF(MonthlyFAME!D461=0,"",MonthlyFAME!D461) -> 60.8828 | E459: =IF(MonthlyFAME!F461=0,"",MonthlyFAME!F461) -> 18977 | F459: =IF(MonthlyFAME!G461=0,"",MonthlyFAME!G461) -> 18202 | G459: =IF(MonthlyFAME!H461=0,"",MonthlyFAME!H461) -> 6.6189624 | H459: =IF(MonthlyFAME!I461=0,"",MonthlyFAME!I461) -> 26622 | I459: =IF(MonthlyFAME!J461=0,"",MonthlyFAME!J461) -> 884.5 | J459: 516.2 | K459: =IF(MonthlyFAME!L461=0,"",MonthlyFAME!L461) -> 278.17034 | L459: =IF(MonthlyFAME!M461=0,"",MonthlyFAME!M461) -> 1431.7 | M459: =IF(MonthlyFAME!N461=0,"",MonthlyFAME!N461) | N459: =IF(MonthlyFAME!O461=0,"",MonthlyFAME!O461) | O459: =IF(MonthlyFAME!P461=0,"",MonthlyFAME!P461) | P459: =IF(MonthlyFAME!Q461=0,"",MonthlyFAME!Q461) | Q459: =IF(MonthlyFAME!R461=0,"",MonthlyFAME!R461) | R459: =IF(MonthlyFAME!S461=0,"",MonthlyFAME!S461) | ... T459: =IF(MonthlyFAME!U461=0,"",MonthlyFAME!U461) -> 19.1495
A460: =IF(MonthlyFAME!A462=0,"",MonthlyFAME!A462) -> 35795 | B460: =IF(MonthlyFAME!B462=0,"",MonthlyFAME!B462) -> 66.2 | C460: =IF(MonthlyFAME!C462=0,"",MonthlyFAME!C462) -> 85.3 | D460: =IF(MonthlyFAME!D462=0,"",MonthlyFAME!D462) -> 61.4453 | E460: =IF(MonthlyFAME!F462=0,"",MonthlyFAME!F462) -> 20445 | F460: =IF(MonthlyFAME!G462=0,"",MonthlyFAME!G462) -> 18889 | G460: =IF(MonthlyFAME!H462=0,"",MonthlyFAME!H462) -> 6.5403509 | H460: =IF(MonthlyFAME!I462=0,"",MonthlyFAME!I462) -> 26636 | I460: =IF(MonthlyFAME!J462=0,"",MonthlyFAME!J462) -> 879.8 | J460: 483.68485 | K460: =IF(MonthlyFAME!L462=0,"",MonthlyFAME!L462) -> 279.89423 | L460: =IF(MonthlyFAME!M462=0,"",MonthlyFAME!M462) -> 1410.5 | M460: =IF(MonthlyFAME!N462=0,"",MonthlyFAME!N462) | N460: =IF(MonthlyFAME!O462=0,"",MonthlyFAME!O462) | O460: =IF(MonthlyFAME!P462=0,"",MonthlyFAME!P462) | P460: =IF(MonthlyFAME!Q462=0,"",MonthlyFAME!Q462) | Q460: =IF(MonthlyFAME!R462=0,"",MonthlyFAME!R462) | R460: =IF(MonthlyFAME!S462=0,"",MonthlyFAME!S462) | ... T460: =IF(MonthlyFAME!U462=0,"",MonthlyFAME!U462) -> 17.094348
... A501: =IF(MonthlyFAME!A503=0,"",MonthlyFAME!A503) -> 37042 | B501: =IF(MonthlyFAME!B503=0,"",MonthlyFAME!B503) -> 73.8 | C501: =IF(MonthlyFAME!C503=0,"",MonthlyFAME!C503) -> 96.8 | D501: =IF(MonthlyFAME!D503=0,"",MonthlyFAME!D503) -> 68.1267 | E501: =IF(MonthlyFAME!F503=0,"",MonthlyFAME!F503) -> 22132 | F501: =IF(MonthlyFAME!G503=0,"",MonthlyFAME!G503) -> 24425 | G501: =IF(MonthlyFAME!H503=0,"",MonthlyFAME!H503) -> 4.9124614 | H501: =IF(MonthlyFAME!I503=0,"",MonthlyFAME!I503) -> 27699 | I501: =IF(MonthlyFAME!J503=0,"",MonthlyFAME!J503) -> 906.5 | J501: 681.58788 | K501: =IF(MonthlyFAME!L503=0,"",MonthlyFAME!L503) -> 326.62827 | L501: =IF(MonthlyFAME!M503=0,"",MonthlyFAME!M503) -> 974.9 | M501: =IF(MonthlyFAME!N503=0,"",MonthlyFAME!N503) | N501: =IF(MonthlyFAME!O503=0,"",MonthlyFAME!O503) | O501: =IF(MonthlyFAME!P503=0,"",MonthlyFAME!P503) | P501: =IF(MonthlyFAME!Q503=0,"",MonthlyFAME!Q503) | Q501: =IF(MonthlyFAME!R503=0,"",MonthlyFAME!R503) | R501: =IF(MonthlyFAME!S503=0,"",MonthlyFAME!S503) | ... T501: =IF(MonthlyFAME!U503=0,"",MonthlyFAME!U503) -> 28.39913
A502: =IF(MonthlyFAME!A504=0,"",MonthlyFAME!A504) -> 37072 | B502: =IF(MonthlyFAME!B504=0,"",MonthlyFAME!B504) -> 74.1 | C502: =IF(MonthlyFAME!C504=0,"",MonthlyFAME!C504) -> 97.5 | D502: =IF(MonthlyFAME!D504=0,"",MonthlyFAME!D504) -> 68.3656 | E502: =IF(MonthlyFAME!F504=0,"",MonthlyFAME!F504) -> 22577 | F502: =IF(MonthlyFAME!G504=0,"",MonthlyFAME!G504) -> 25351 | G502: =IF(MonthlyFAME!H504=0,"",MonthlyFAME!H504) -> 5.0317052 | H502: =IF(MonthlyFAME!I504=0,"",MonthlyFAME!I504) -> 27707 | I502: =IF(MonthlyFAME!J504=0,"",MonthlyFAME!J504) -> 906.4 | J502: =IF(MonthlyFAME!K504=0,"",MonthlyFAME!K504) -> 680 | K502: =IF(MonthlyFAME!L504=0,"",MonthlyFAME!L504) -> 328.44501 | L502: =IF(MonthlyFAME!M504=0,"",MonthlyFAME!M504) -> 961.6 | ... T502: =IF(MonthlyFAME!U504=0,"",MonthlyFAME!U504) -> 27.771905
A503: =IF(MonthlyFAME!A505=0,"",MonthlyFAME!A505) -> 37103 | B503: =IF(MonthlyFAME!B505=0,"",MonthlyFAME!B505) -> 74.1 | C503: =IF(MonthlyFAME!C505=0,"",MonthlyFAME!C505) -> 97.2 | D503: =IF(MonthlyFAME!D505=0,"",MonthlyFAME!D505) -> 68.4044 | E503: =IF(MonthlyFAME!F505=0,"",MonthlyFAME!F505) -> 22115 | F503: =IF(MonthlyFAME!G505=0,"",MonthlyFAME!G505) -> 24320 | G503: =IF(MonthlyFAME!H505=0,"",MonthlyFAME!H505) -> 5.0461074 | H503: =IF(MonthlyFAME!I505=0,"",MonthlyFAME!I505) -> 27699 | I503: =IF(MonthlyFAME!J505=0,"",MonthlyFAME!J505) -> 905.8 | J503: =IF(MonthlyFAME!K505=0,"",MonthlyFAME!K505) -> 674 | K503: =IF(MonthlyFAME!L505=0,"",MonthlyFAME!L505) -> 328.39632 | L503: =IF(MonthlyFAME!M505=0,"",MonthlyFAME!M505) -> 951.8 | ... T503: =IF(MonthlyFAME!U505=0,"",MonthlyFAME!U505) -> 24.615
A504: =IF(MonthlyFAME!A506=0,"",MonthlyFAME!A506) -> 37134 | B504: =IF(MonthlyFAME!B506=0,"",MonthlyFAME!B506) -> 74.3 | C504: =IF(MonthlyFAME!C506=0,"",MonthlyFAME!C506) -> 98.3 | D504: =IF(MonthlyFAME!D506=0,"",MonthlyFAME!D506) -> 68.4794 | E504: =IF(MonthlyFAME!F506=0,"",MonthlyFAME!F506) -> 21732 | F504: =IF(MonthlyFAME!G506=0,"",MonthlyFAME!G506) -> 24820 | G504: =IF(MonthlyFAME!H506=0,"",MonthlyFAME!H506) -> 5.0784193 | H504: =IF(MonthlyFAME!I506=0,"",MonthlyFAME!I506) -> 27719 | I504: =IF(MonthlyFAME!J506=0,"",MonthlyFAME!J506) -> 906.4 | J504: =IF(MonthlyFAME!K506=0,"",MonthlyFAME!K506) -> 663 | K504: =IF(MonthlyFAME!L506=0,"",MonthlyFAME!L506) -> 330.72633 | L504: =IF(MonthlyFAME!M506=0,"",MonthlyFAME!M506) -> 951.2 | ... T504: =IF(MonthlyFAME!U506=0,"",MonthlyFAME!U506) -> 25.673043
A505: =IF(MonthlyFAME!A507=0,"",MonthlyFAME!A507) -> 37164 | B505: =IF(MonthlyFAME!B507=0,"",MonthlyFAME!B507) -> 74.2 | C505: =IF(MonthlyFAME!C507=0,"",MonthlyFAME!C507) -> 97.8 | D505: =IF(MonthlyFAME!D507=0,"",MonthlyFAME!D507) -> 68.5095 | E505: =IF(MonthlyFAME!F507=0,"",MonthlyFAME!F507) -> 21426 | F505: =IF(MonthlyFAME!G507=0,"",MonthlyFAME!G507) -> 23532 | G505: =IF(MonthlyFAME!H507=0,"",MonthlyFAME!H507) -> 5.092117 | H505: =IF(MonthlyFAME!I507=0,"",MonthlyFAME!I507) -> 27715 | I505: =IF(MonthlyFAME!J507=0,"",MonthlyFAME!J507) -> 904.9 | J505: =IF(MonthlyFAME!K507=0,"",MonthlyFAME!K507) -> 663 | K505: =IF(MonthlyFAME!L507=0,"",MonthlyFAME!L507) -> 331.10736 | L505: =IF(MonthlyFAME!M507=0,"",MonthlyFAME!M507) -> 946.1 | ... T505: =IF(MonthlyFAME!U507=0,"",MonthlyFAME!U507) -> 25.5115
A506: =IF(MonthlyFAME!A508=0,"",MonthlyFAME!A508) -> 37195 | B506: =IF(MonthlyFAME!B508=0,"",MonthlyFAME!B508) -> 74.4 | C506: =IF(MonthlyFAME!C508=0,"",MonthlyFAME!C508) -> 97.2 | D506: =IF(MonthlyFAME!D508=0,"",MonthlyFAME!D508) -> 68.8234 | E506: =IF(MonthlyFAME!F508=0,"",MonthlyFAME!F508) -> 22806 | F506: =IF(MonthlyFAME!G508=0,"",MonthlyFAME!G508) -> 24848 | G506: =IF(MonthlyFAME!H508=0,"",MonthlyFAME!H508) -> 5.0886319 | H506: =IF(MonthlyFAME!I508=0,"",MonthlyFAME!I508) -> 27735 | I506: =IF(MonthlyFAME!J508=0,"",MonthlyFAME!J508) -> 904.2 | J506: =IF(MonthlyFAME!K508=0,"",MonthlyFAME!K508) -> 639 | K506: =IF(MonthlyFAME!L508=0,"",MonthlyFAME!L508) -> 332.70195 | L506: =IF(MonthlyFAME!M508=0,"",MonthlyFAME!M508) -> 953 | ... T506: =IF(MonthlyFAME!U508=0,"",MonthlyFAME!U508) -> 20.452174
A507: =IF(MonthlyFAME!A509=0,"",MonthlyFAME!A509) -> 37225 | B507: =IF(MonthlyFAME!B509=0,"",MonthlyFAME!B509) -> 74.4 | C507: =IF(MonthlyFAME!C509=0,"",MonthlyFAME!C509) -> 97.3 | D507: =IF(MonthlyFAME!D509=0,"",MonthlyFAME!D509) -> 68.7432 | E507: =IF(MonthlyFAME!F509=0,"",MonthlyFAME!F509) -> 22025 | F507: =IF(MonthlyFAME!G509=0,"",MonthlyFAME!G509) -> 24191 | G507: =IF(MonthlyFAME!H509=0,"",MonthlyFAME!H509) -> 5.1055256 | H507: =IF(MonthlyFAME!I509=0,"",MonthlyFAME!I509) -> 27787 | I507: =IF(MonthlyFAME!J509=0,"",MonthlyFAME!J509) -> 903.5 | J507: =IF(MonthlyFAME!K509=0,"",MonthlyFAME!K509) -> 626 | K507: =IF(MonthlyFAME!L509=0,"",MonthlyFAME!L509) -> 333.7407 | L507: =IF(MonthlyFAME!M509=0,"",MonthlyFAME!M509) -> 959.7 | ... T507: =IF(MonthlyFAME!U509=0,"",MonthlyFAME!U509) -> 18.914091
A508: =IF(MonthlyFAME!A510=0,"",MonthlyFAME!A510) -> 37256 | B508: =IF(MonthlyFAME!B510=0,"",MonthlyFAME!B510) -> 74.3 | C508: =IF(MonthlyFAME!C510=0,"",MonthlyFAME!C510) -> 96.9 | D508: =IF(MonthlyFAME!D510=0,"",MonthlyFAME!D510) -> 68.6953 | E508: =IF(MonthlyFAME!F510=0,"",MonthlyFAME!F510) -> 21049 | F508: =IF(MonthlyFAME!G510=0,"",MonthlyFAME!G510) -> 23801 | G508: =IF(MonthlyFAME!H510=0,"",MonthlyFAME!H510) -> 5.1836442 | H508: =IF(MonthlyFAME!I510=0,"",MonthlyFAME!I510) -> 27803 | I508: =IF(MonthlyFAME!J510=0,"",MonthlyFAME!J510) -> 903.5 | J508: =IF(MonthlyFAME!K510=0,"",MonthlyFAME!K510) -> 602 | K508: =IF(MonthlyFAME!L510=0,"",MonthlyFAME!L510) -> 334.15437 | L508: =IF(MonthlyFAME!M510=0,"",MonthlyFAME!M510) -> 966.5 | ... T508: =IF(MonthlyFAME!U510=0,"",MonthlyFAME!U510) -> 18.531429
A509: =IF(MonthlyFAME!A511=0,"",MonthlyFAME!A511) -> 37287 | B509: =IF(MonthlyFAME!B511=0,"",MonthlyFAME!B511) -> 74.5 | C509: =IF(MonthlyFAME!C511=0,"",MonthlyFAME!C511) -> 96.3 | D509: =IF(MonthlyFAME!D511=0,"",MonthlyFAME!D511) -> 68.9917 | E509: =IF(MonthlyFAME!F511=0,"",MonthlyFAME!F511) -> 22703 | F509: =IF(MonthlyFAME!G511=0,"",MonthlyFAME!G511) -> 24581 | G509: =IF(MonthlyFAME!H511=0,"",MonthlyFAME!H511) -> 5.1831871 | H509: =IF(MonthlyFAME!I511=0,"",MonthlyFAME!I511) -> 27769 | I509: =IF(MonthlyFAME!J511=0,"",MonthlyFAME!J511) -> 899.7 | J509: =IF(MonthlyFAME!K511=0,"",MonthlyFAME!K511) -> 605 | K509: =IF(MonthlyFAME!L511=0,"",MonthlyFAME!L511) -> 332.56489 | L509: =IF(MonthlyFAME!M511=0,"",MonthlyFAME!M511) -> 958.2 | ... T509: =IF(MonthlyFAME!U511=0,"",MonthlyFAME!U511) -> 19.462609
A510: =IF(MonthlyFAME!A512=0,"",MonthlyFAME!A512) -> 37315 | B510: =IF(MonthlyFAME!B512=0,"",MonthlyFAME!B512) -> 74.4 | C510: =IF(MonthlyFAME!C512=0,"",MonthlyFAME!C512) -> 96.4 | D510: =IF(MonthlyFAME!D512=0,"",MonthlyFAME!D512) -> 68.8412 | E510: =IF(MonthlyFAME!F512=0,"",MonthlyFAME!F512) -> 22397 | F510: =IF(MonthlyFAME!G512=0,"",MonthlyFAME!G512) -> 25339 | G510: =IF(MonthlyFAME!H512=0,"",MonthlyFAME!H512) -> 5.1486906 | H510: =IF(MonthlyFAME!I512=0,"",MonthlyFAME!I512) -> 27781 | I510: =IF(MonthlyFAME!J512=0,"",MonthlyFAME!J512) -> 900.1 | J510: =IF(MonthlyFAME!K512=0,"",MonthlyFAME!K512) -> 616 | K510: =IF(MonthlyFAME!L512=0,"",MonthlyFAME!L512) -> 334.08736 | L510: =IF(MonthlyFAME!M512=0,"",MonthlyFAME!M512) -> 951.9 | ... T510: =IF(MonthlyFAME!U512=0,"",MonthlyFAME!U512) -> 20.111
A511: =IF(MonthlyFAME!A513=0,"",MonthlyFAME!A513) -> 37346 | B511: =IF(MonthlyFAME!B513=0,"",MonthlyFAME!B513) -> 74.6 | C511: =IF(MonthlyFAME!C513=0,"",MonthlyFAME!C513) -> 98.2 | D511: =IF(MonthlyFAME!D513=0,"",MonthlyFAME!D513) -> 68.7459 | E511: =IF(MonthlyFAME!F513=0,"",MonthlyFAME!F513) -> 22615 | F511: =IF(MonthlyFAME!G513=0,"",MonthlyFAME!G513) -> 25448 | G511: =IF(MonthlyFAME!H513=0,"",MonthlyFAME!H513) -> 5.1685317 | H511: =IF(MonthlyFAME!I513=0,"",MonthlyFAME!I513) -> 27797 | I511: =IF(MonthlyFAME!J513=0,"",MonthlyFAME!J513) -> 901.5 | J511: =IF(MonthlyFAME!K513=0,"",MonthlyFAME!K513) -> 617 | K511: =IF(MonthlyFAME!L513=0,"",MonthlyFAME!L513) -> 334.31133 | L511: =IF(MonthlyFAME!M513=0,"",MonthlyFAME!M513) -> 947.5 | ... T511: =IF(MonthlyFAME!U513=0,"",MonthlyFAME!U513) -> 23.84381
A512: =IF(MonthlyFAME!A514=0,"",MonthlyFAME!A514) -> 37376 | B512: =IF(MonthlyFAME!B514=0,"",MonthlyFAME!B514) -> 75 | C512: =IF(MonthlyFAME!C514=0,"",MonthlyFAME!C514) -> 96.1 | D512: =IF(MonthlyFAME!D514=0,"",MonthlyFAME!D514) -> 69.7015 | E512: =IF(MonthlyFAME!F514=0,"",MonthlyFAME!F514) -> 23208 | F512: =IF(MonthlyFAME!G514=0,"",MonthlyFAME!G514) -> 26560 | G512: =IF(MonthlyFAME!H514=0,"",MonthlyFAME!H514) -> 5.1807475 | H512: =IF(MonthlyFAME!I514=0,"",MonthlyFAME!I514) -> 27856 | I512: =IF(MonthlyFAME!J514=0,"",MonthlyFAME!J514) -> 903.9 | J512: =IF(MonthlyFAME!K514=0,"",MonthlyFAME!K514) -> 622 | K512: =IF(MonthlyFAME!L514=0,"",MonthlyFAME!L514) -> 338.34114 | L512: =IF(MonthlyFAME!M514=0,"",MonthlyFAME!M514) -> 954.9 | ... T512: =IF(MonthlyFAME!U514=0,"",MonthlyFAME!U514) -> 25.598182
A513: =IF(MonthlyFAME!A515=0,"",MonthlyFAME!A515) -> 37407 | B513: =IF(MonthlyFAME!B515=0,"",MonthlyFAME!B515) -> 75.5 | C513: =IF(MonthlyFAME!C515=0,"",MonthlyFAME!C515) -> 99.1 | D513: =IF(MonthlyFAME!D515=0,"",MonthlyFAME!D515) -> 69.8082 | E513: =IF(MonthlyFAME!F515=0,"",MonthlyFAME!F515) -> 25099 | F513: =IF(MonthlyFAME!G515=0,"",MonthlyFAME!G515) -> 26852 | G513: =IF(MonthlyFAME!H515=0,"",MonthlyFAME!H515) -> 5.2395515 | H513: =IF(MonthlyFAME!I515=0,"",MonthlyFAME!I515) -> 27888 | I513: =IF(MonthlyFAME!J515=0,"",MonthlyFAME!J515) -> 908.3 | J513: =IF(MonthlyFAME!K515=0,"",MonthlyFAME!K515) -> 613 | K513: =IF(MonthlyFAME!L515=0,"",MonthlyFAME!L515) -> 338.78087 | L513: =IF(MonthlyFAME!M515=0,"",MonthlyFAME!M515) -> 947.1 | ... T513: =IF(MonthlyFAME!U515=0,"",MonthlyFAME!U515) -> 25.33913
... A757: =IF(MonthlyFAME!A759=0,"",MonthlyFAME!A759) -> 44834 | B757: =IF(MonthlyFAME!B759=0,"",MonthlyFAME!B759) -> 101.5 | C757: =IF(MonthlyFAME!C759=0,"",MonthlyFAME!C759) -> 93.8 | D757: =IF(MonthlyFAME!D759=0,"",MonthlyFAME!D759) -> 102.8416 | E757: =IF(MonthlyFAME!F759=0,"",MonthlyFAME!F759) -> 34019 | F757: =IF(MonthlyFAME!G759=0,"",MonthlyFAME!G759) -> 40114 | G757: =IF(MonthlyFAME!H759=0,"",MonthlyFAME!H759) -> 3.7515717 | H757: =IF(MonthlyFAME!I759=0,"",MonthlyFAME!I759) -> 32916 | I757: =IF(MonthlyFAME!J759=0,"",MonthlyFAME!J759) -> 1043.7 | J757: =IF(MonthlyFAME!K759=0,"",MonthlyFAME!K759) -> 1233 | K757: =IF(MonthlyFAME!L759=0,"",MonthlyFAME!L759) -> 620.86544 | L757: =IF(MonthlyFAME!M759=0,"",MonthlyFAME!M759) -> 1529.7 | ... T757: =IF(MonthlyFAME!U759=0,"",MonthlyFAME!U759) -> 89.749545
A758: =IF(MonthlyFAME!A760=0,"",MonthlyFAME!A760) -> 44865 | B758: =IF(MonthlyFAME!B760=0,"",MonthlyFAME!B760) -> 102.3 | C758: =IF(MonthlyFAME!C760=0,"",MonthlyFAME!C760) -> 94.2 | D758: =IF(MonthlyFAME!D760=0,"",MonthlyFAME!D760) -> 103.723 | E758: =IF(MonthlyFAME!F760=0,"",MonthlyFAME!F760) -> 33624 | F758: =IF(MonthlyFAME!G760=0,"",MonthlyFAME!G760) -> 39923 | G758: =IF(MonthlyFAME!H760=0,"",MonthlyFAME!H760) -> 3.8572637 | H758: =IF(MonthlyFAME!I760=0,"",MonthlyFAME!I760) -> 32951 | I758: =IF(MonthlyFAME!J760=0,"",MonthlyFAME!J760) -> 1042.1 | J758: =IF(MonthlyFAME!K760=0,"",MonthlyFAME!K760) -> 1216 | L758: =IF(MonthlyFAME!M760=0,"",MonthlyFAME!M760) -> 1517.9 | M758: =IF(MonthlyFAME!N760=0,"",MonthlyFAME!N760) | N758: =IF(MonthlyFAME!O760=0,"",MonthlyFAME!O760) | O758: =IF(MonthlyFAME!P760=0,"",MonthlyFAME!P760) | P758: =IF(MonthlyFAME!Q760=0,"",MonthlyFAME!Q760) | Q758: =IF(MonthlyFAME!R760=0,"",MonthlyFAME!R760) | R758: =IF(MonthlyFAME!S760=0,"",MonthlyFAME!S760) | S758: =IF(MonthlyFAME!T760=0,"",MonthlyFAME!T760) | T758: =IF(MonthlyFAME!U760=0,"",MonthlyFAME!U760) -> 93.395714
A759: =IF(MonthlyFAME!A761=0,"",MonthlyFAME!A761) -> 44895 | B759: =IF(MonthlyFAME!B761=0,"",MonthlyFAME!B761) -> 102.3 | C759: =IF(MonthlyFAME!C761=0,"",MonthlyFAME!C761) -> 94 | D759: =IF(MonthlyFAME!D761=0,"",MonthlyFAME!D761) -> 103.7449 | E759: =IF(MonthlyFAME!F761=0,"",MonthlyFAME!F761) -> 33445 | F759: =IF(MonthlyFAME!G761=0,"",MonthlyFAME!G761) -> 42508 | G759: =IF(MonthlyFAME!H761=0,"",MonthlyFAME!H761) -> 3.8040949 | H759: =IF(MonthlyFAME!I761=0,"",MonthlyFAME!I761) -> 33076 | I759: =IF(MonthlyFAME!J761=0,"",MonthlyFAME!J761) -> 1044 | J759: =IF(MonthlyFAME!K761=0,"",MonthlyFAME!K761) -> 1175 | L759: =IF(MonthlyFAME!M761=0,"",MonthlyFAME!M761) -> 1528.9 | M759: =IF(MonthlyFAME!N761=0,"",MonthlyFAME!N761) | N759: =IF(MonthlyFAME!O761=0,"",MonthlyFAME!O761) | O759: =IF(MonthlyFAME!P761=0,"",MonthlyFAME!P761) | P759: =IF(MonthlyFAME!Q761=0,"",MonthlyFAME!Q761) | Q759: =IF(MonthlyFAME!R761=0,"",MonthlyFAME!R761) | R759: =IF(MonthlyFAME!S761=0,"",MonthlyFAME!S761) | S759: =IF(MonthlyFAME!T761=0,"",MonthlyFAME!T761) | T759: =IF(MonthlyFAME!U761=0,"",MonthlyFAME!U761) -> 91.415455
A760: =IF(MonthlyFAME!A762=0,"",MonthlyFAME!A762) -> 44926 | B760: =IF(MonthlyFAME!B762=0,"",MonthlyFAME!B762) -> 102 | C760: =IF(MonthlyFAME!C762=0,"",MonthlyFAME!C762) -> 94.1 | D760: =IF(MonthlyFAME!D762=0,"",MonthlyFAME!D762) -> 103.1301 | E760: =IF(MonthlyFAME!F762=0,"",MonthlyFAME!F762) -> 31396 | F760: =IF(MonthlyFAME!G762=0,"",MonthlyFAME!G762) -> 43734 | G760: =IF(MonthlyFAME!H762=0,"",MonthlyFAME!H762) -> 3.875 | H760: =IF(MonthlyFAME!I762=0,"",MonthlyFAME!I762) -> 33067 | I760: =IF(MonthlyFAME!J762=0,"",MonthlyFAME!J762) -> 1046.6 | J760: =IF(MonthlyFAME!K762=0,"",MonthlyFAME!K762) -> 1153 | L760: =IF(MonthlyFAME!M762=0,"",MonthlyFAME!M762) -> 1536.4 | M760: =IF(MonthlyFAME!N762=0,"",MonthlyFAME!N762) | N760: =IF(MonthlyFAME!O762=0,"",MonthlyFAME!O762) | O760: =IF(MonthlyFAME!P762=0,"",MonthlyFAME!P762) | P760: =IF(MonthlyFAME!Q762=0,"",MonthlyFAME!Q762) | Q760: =IF(MonthlyFAME!R762=0,"",MonthlyFAME!R762) | R760: =IF(MonthlyFAME!S762=0,"",MonthlyFAME!S762) | S760: =IF(MonthlyFAME!T762=0,"",MonthlyFAME!T762) | T760: =IF(MonthlyFAME!U762=0,"",MonthlyFAME!U762) -> 81.062727
A761: =IF(MonthlyFAME!A763=0,"",MonthlyFAME!A763) -> 44957 | B761: =IF(MonthlyFAME!B763=0,"",MonthlyFAME!B763) -> 102.3 | C761: =IF(MonthlyFAME!C763=0,"",MonthlyFAME!C763) -> 94 | D761: =IF(MonthlyFAME!D763=0,"",MonthlyFAME!D763) -> 103.8888 | E761: =IF(MonthlyFAME!F763=0,"",MonthlyFAME!F763) -> 28556 | F761: =IF(MonthlyFAME!G763=0,"",MonthlyFAME!G763) -> 40141 | G761: =IF(MonthlyFAME!H763=0,"",MonthlyFAME!H763) -> 3.8183245 | H761: =IF(MonthlyFAME!I763=0,"",MonthlyFAME!I763) -> 33099 | I761: =IF(MonthlyFAME!J763=0,"",MonthlyFAME!J763) -> 1051.4 | J761: =IF(MonthlyFAME!K763=0,"",MonthlyFAME!K763) -> 1132 | L761: =IF(MonthlyFAME!M763=0,"",MonthlyFAME!M763) -> 1516.6 | M761: =IF(MonthlyFAME!N763=0,"",MonthlyFAME!N763) | N761: =IF(MonthlyFAME!O763=0,"",MonthlyFAME!O763) | O761: =IF(MonthlyFAME!P763=0,"",MonthlyFAME!P763) | P761: =IF(MonthlyFAME!Q763=0,"",MonthlyFAME!Q763) | Q761: =IF(MonthlyFAME!R763=0,"",MonthlyFAME!R763) | R761: =IF(MonthlyFAME!S763=0,"",MonthlyFAME!S763) | S761: =IF(MonthlyFAME!T763=0,"",MonthlyFAME!T763) | T761: =IF(MonthlyFAME!U763=0,"",MonthlyFAME!U763) -> 82.502727
A762: =IF(MonthlyFAME!A764=0,"",MonthlyFAME!A764) -> 44985 | B762: =IF(MonthlyFAME!B764=0,"",MonthlyFAME!B764) -> 102.6 | C762: =IF(MonthlyFAME!C764=0,"",MonthlyFAME!C764) -> 94.1 | D762: =IF(MonthlyFAME!D764=0,"",MonthlyFAME!D764) -> 103.9971 | E762: =IF(MonthlyFAME!F764=0,"",MonthlyFAME!F764) -> 27953 | F762: =IF(MonthlyFAME!G764=0,"",MonthlyFAME!G764) -> 39828 | G762: =IF(MonthlyFAME!H764=0,"",MonthlyFAME!H764) -> 3.898963 | H762: =IF(MonthlyFAME!I764=0,"",MonthlyFAME!I764) -> 33176 | I762: =IF(MonthlyFAME!J764=0,"",MonthlyFAME!J764) -> 1055.5 | J762: =IF(MonthlyFAME!K764=0,"",MonthlyFAME!K764) -> 1128 | L762: =IF(MonthlyFAME!M764=0,"",MonthlyFAME!M764) -> 1501.3 | M762: =IF(MonthlyFAME!N764=0,"",MonthlyFAME!N764) | N762: =IF(MonthlyFAME!O764=0,"",MonthlyFAME!O764) | O762: =IF(MonthlyFAME!P764=0,"",MonthlyFAME!P764) | P762: =IF(MonthlyFAME!Q764=0,"",MonthlyFAME!Q764) | Q762: =IF(MonthlyFAME!R764=0,"",MonthlyFAME!R764) | R762: =IF(MonthlyFAME!S764=0,"",MonthlyFAME!S764) | S762: =IF(MonthlyFAME!T764=0,"",MonthlyFAME!T764) | T762: =IF(MonthlyFAME!U764=0,"",MonthlyFAME!U764) -> 82.666
A763: =IF(MonthlyFAME!A765=0,"",MonthlyFAME!A765) -> 45016 | B763: =IF(MonthlyFAME!B765=0,"",MonthlyFAME!B765) -> 102.2 | C763: =IF(MonthlyFAME!C765=0,"",MonthlyFAME!C765) -> 94.7 | D763: =IF(MonthlyFAME!D765=0,"",MonthlyFAME!D765) -> 103.4819 | E763: =IF(MonthlyFAME!F765=0,"",MonthlyFAME!F765) -> 27702 | F763: =IF(MonthlyFAME!G765=0,"",MonthlyFAME!G765) -> 40261 | G763: =IF(MonthlyFAME!H765=0,"",MonthlyFAME!H765) -> 3.9989591 | H763: =IF(MonthlyFAME!I765=0,"",MonthlyFAME!I765) -> 33201 | I763: =IF(MonthlyFAME!J765=0,"",MonthlyFAME!J765) -> 1055.3 | J763: =IF(MonthlyFAME!K765=0,"",MonthlyFAME!K765) -> 1120 | L763: =IF(MonthlyFAME!M765=0,"",MonthlyFAME!M765) -> 1513.4 | M763: =IF(MonthlyFAME!N765=0,"",MonthlyFAME!N765) | N763: =IF(MonthlyFAME!O765=0,"",MonthlyFAME!O765) | O763: =IF(MonthlyFAME!P765=0,"",MonthlyFAME!P765) | P763: =IF(MonthlyFAME!Q765=0,"",MonthlyFAME!Q765) | Q763: =IF(MonthlyFAME!R765=0,"",MonthlyFAME!R765) | R763: =IF(MonthlyFAME!S765=0,"",MonthlyFAME!S765) | S763: =IF(MonthlyFAME!T765=0,"",MonthlyFAME!T765) | T763: =IF(MonthlyFAME!U765=0,"",MonthlyFAME!U765) -> 78.434348
A764: =IF(MonthlyFAME!A766=0,"",MonthlyFAME!A766) -> 45046 | B764: =IF(MonthlyFAME!B766=0,"",MonthlyFAME!B766) -> 102.4 | C764: =IF(MonthlyFAME!C766=0,"",MonthlyFAME!C766) -> 94.8 | D764: =IF(MonthlyFAME!D766=0,"",MonthlyFAME!D766) -> 103.6422 | E764: =IF(MonthlyFAME!F766=0,"",MonthlyFAME!F766) -> 28212 | G764: =IF(MonthlyFAME!H766=0,"",MonthlyFAME!H766) -> 3.9014966 | H764: =IF(MonthlyFAME!I766=0,"",MonthlyFAME!I766) -> 33326 | I764: =IF(MonthlyFAME!J766=0,"",MonthlyFAME!J766) -> 1063 | J764: =IF(MonthlyFAME!K766=0,"",MonthlyFAME!K766) -> 1086 | L764: =IF(MonthlyFAME!M766=0,"",MonthlyFAME!M766) -> 1549.5 | M764: =IF(MonthlyFAME!N766=0,"",MonthlyFAME!N766) | N764: =IF(MonthlyFAME!O766=0,"",MonthlyFAME!O766) | O764: =IF(MonthlyFAME!P766=0,"",MonthlyFAME!P766) | P764: =IF(MonthlyFAME!Q766=0,"",MonthlyFAME!Q766) | Q764: =IF(MonthlyFAME!R766=0,"",MonthlyFAME!R766) | R764: =IF(MonthlyFAME!S766=0,"",MonthlyFAME!S766) | S764: =IF(MonthlyFAME!T766=0,"",MonthlyFAME!T766) | T764: =IF(MonthlyFAME!U766=0,"",MonthlyFAME!U766) -> 84.8305
A765: =IF(MonthlyFAME!A767=0,"",MonthlyFAME!A767) -> 45077 | B765: =IF(MonthlyFAME!B767=0,"",MonthlyFAME!B767) -> 102 | C765: =IF(MonthlyFAME!C767=0,"",MonthlyFAME!C767) -> 93.9 | D765: =IF(MonthlyFAME!D767=0,"",MonthlyFAME!D767) -> 103.4877 | E765: =IF(MonthlyFAME!F767=0,"",MonthlyFAME!F767) -> 27374 | G765: =IF(MonthlyFAME!H767=0,"",MonthlyFAME!H767) -> 4.0194779 | H765: =IF(MonthlyFAME!I767=0,"",MonthlyFAME!I767) -> 33311 | I765: =IF(MonthlyFAME!J767=0,"",MonthlyFAME!J767) -> 1057.6 | J765: =IF(MonthlyFAME!K767=0,"",MonthlyFAME!K767) -> 1060 | L765: =IF(MonthlyFAME!M767=0,"",MonthlyFAME!M767) -> 1522.2 | M765: =IF(MonthlyFAME!N767=0,"",MonthlyFAME!N767) | N765: =IF(MonthlyFAME!O767=0,"",MonthlyFAME!O767) | O765: =IF(MonthlyFAME!P767=0,"",MonthlyFAME!P767) | P765: =IF(MonthlyFAME!Q767=0,"",MonthlyFAME!Q767) | Q765: =IF(MonthlyFAME!R767=0,"",MonthlyFAME!R767) | R765: =IF(MonthlyFAME!S767=0,"",MonthlyFAME!S767) | S765: =IF(MonthlyFAME!T767=0,"",MonthlyFAME!T767) | T765: =IF(MonthlyFAME!U767=0,"",MonthlyFAME!U767) -> 75.861304
A766: =IF(MonthlyFAME!A768=0,"",MonthlyFAME!A768) -> 45107 | B766: =IF(MonthlyFAME!B768=0,"",MonthlyFAME!B768) -> 102.8 | C766: =IF(MonthlyFAME!C768=0,"",MonthlyFAME!C768) -> 96.4 | D766: =IF(MonthlyFAME!D768=0,"",MonthlyFAME!D768) -> 103.8202 | E766: =IF(MonthlyFAME!F768=0,"",MonthlyFAME!F768) -> 28123 | G766: =IF(MonthlyFAME!H768=0,"",MonthlyFAME!H768) -> 4.2168501 | H766: =IF(MonthlyFAME!I768=0,"",MonthlyFAME!I768) -> 33163 | I766: =IF(MonthlyFAME!J768=0,"",MonthlyFAME!J768) -> 1049 | J766: =IF(MonthlyFAME!K768=0,"",MonthlyFAME!K768) -> 1037 | L766: =IF(MonthlyFAME!M768=0,"",MonthlyFAME!M768) -> 1534.6 | M766: =IF(MonthlyFAME!N768=0,"",MonthlyFAME!N768) | N766: =IF(MonthlyFAME!O768=0,"",MonthlyFAME!O768) | O766: =IF(MonthlyFAME!P768=0,"",MonthlyFAME!P768) | P766: =IF(MonthlyFAME!Q768=0,"",MonthlyFAME!Q768) | Q766: =IF(MonthlyFAME!R768=0,"",MonthlyFAME!R768) | R766: =IF(MonthlyFAME!S768=0,"",MonthlyFAME!S768) | S766: =IF(MonthlyFAME!T768=0,"",MonthlyFAME!T768) | T766: =IF(MonthlyFAME!U768=0,"",MonthlyFAME!U768) -> 75.140227
A767: =IF(MonthlyFAME!A769=0,"",MonthlyFAME!A769) -> 45138 | B767: =IF(MonthlyFAME!B769=0,"",MonthlyFAME!B769) -> 102.3 | C767: =IF(MonthlyFAME!C769=0,"",MonthlyFAME!C769) -> 95.4 | D767: =IF(MonthlyFAME!D769=0,"",MonthlyFAME!D769) -> 103.3652 | E767: =IF(MonthlyFAME!F769=0,"",MonthlyFAME!F769) -> 28468 | G767: =IF(MonthlyFAME!H769=0,"",MonthlyFAME!H769) -> 4.3264503 | H767: =IF(MonthlyFAME!I769=0,"",MonthlyFAME!I769) -> 33082 | I767: =IF(MonthlyFAME!J769=0,"",MonthlyFAME!J769) -> 1043.9 | J767: =IF(MonthlyFAME!K769=0,"",MonthlyFAME!K769) -> 1024 | L767: =IF(MonthlyFAME!M769=0,"",MonthlyFAME!M769) -> 1545.9 | M767: =IF(MonthlyFAME!N769=0,"",MonthlyFAME!N769) | N767: =IF(MonthlyFAME!O769=0,"",MonthlyFAME!O769) | O767: =IF(MonthlyFAME!P769=0,"",MonthlyFAME!P769) | P767: =IF(MonthlyFAME!Q769=0,"",MonthlyFAME!Q769) | Q767: =IF(MonthlyFAME!R769=0,"",MonthlyFAME!R769) | R767: =IF(MonthlyFAME!S769=0,"",MonthlyFAME!S769) | S767: =IF(MonthlyFAME!T769=0,"",MonthlyFAME!T769) | T767: =IF(MonthlyFAME!U769=0,"",MonthlyFAME!U769) -> 80.108095
E768: =IF(MonthlyFAME!F770=0,"",MonthlyFAME!F770) -> 26592

Sheet QuarterlyFAME
A2: 1960
A3: 2023 | B3: 1
A4: q | B4: GDP-q | C4: CONS | D4: INV | E4: HOURS
B5: abmi.q | C5: ons.uk.hhd.abjr.q | D5: ons.uk.ado.npqt.q | E5: ybus.q*13 | F5: a23_outputgap_fin.q | G5: a23_ckp_fin.q
A6: =[2]!FAMEData("FAMEDATE",A2,A3, 0,A4, "Down", "No Heading", "Normal") -> 22006 | B6: =[2]!FAMEData(B5, $A$2, $A$3, 0,$A$4,"Down","No Heading","Normal") -> 151420 | C6: =[2]!FAMEData(C5, $A$2, $A$3, 0,$A$4,"Down","No Heading","Normal") -> 77407 | D6: =[2]!FAMEData(D5, $A$2, $A$3, 0,$A$4,"Down","No Heading","Normal") -> 22788 | E6: =[2]!FAMEData(E5, $A$2, $A$3, 0,$A$4,"Down","No Heading","Normal") | F6: =[2]!FAMEData(F5, $A$2, $A$3, 0,$A$4,"Down","No Heading","Normal") | G6: =[2]!FAMEData(G5, $A$2, $A$3, 0,$A$4,"Down","No Heading","Normal")
A7: 22097 | B7: 150230 | C7: 77150 | D7: 23452
A8: 22189 | B8: 152485 | C8: 77664 | D8: 23888
A9: 22281 | B9: 153552 | C9: 77682 | D9: 24647
A10: 22371 | B10: 155990 | C10: 79058 | D10: 25266
A11: 22462 | B11: 156572 | C11: 79093 | D11: 25693
A12: 22554 | B12: 155818 | C12: 79472 | D12: 26062
A13: 22646 | B13: 155436 | C13: 79509 | D13: 25426
A14: 22736 | B14: 156202 | C14: 80153 | D14: 25626
A15: 22827 | B15: 157678 | C15: 81490 | D15: 26205
A16: 22919 | B16: 158572 | C16: 80962 | D16: 26085
A17: 23011 | B17: 157894 | C17: 81896 | D17: 25479
A18: 23101 | B18: 158616 | C18: 82351 | D18: 23515
... A49: 25933 | B49: 208869 | C49: 100058 | D49: 41365
A50: 26023 | B50: 207680 | C50: 99798 | D50: 40579 | E50: 11235.9
A51: 26114 | B51: 211465 | C51: 102036 | D51: 42575 | E51: 11216.4
A52: 26206 | B52: 215240 | C52: 103845 | D52: 43553 | E52: 11196.9
A53: 26298 | B53: 216006 | C53: 104685 | D53: 44186 | E53: 11202.1
A54: 26389 | B54: 216317 | C54: 106484 | D54: 43781 | E54: 11293.1
A55: 26480 | B55: 222086 | C55: 108905 | D55: 45230 | E55: 11350.3
A56: 26572 | B56: 222694 | C56: 110560 | D56: 45116 | E56: 11397.1
A57: 26664 | B57: 226205 | C57: 111472 | D57: 44980 | E57: 11464.7
A58: 26754 | B58: 237322 | C58: 115851 | D58: 47315 | E58: 11577.8
A59: 26845 | B59: 237728 | C59: 115074 | D59: 45755 | E59: 11624.6
A60: 26937 | B60: 235429 | C60: 115927 | D60: 44849 | E60: 11618.1
A61: 27029 | B61: 234514 | C61: 115008 | D61: 44646 | E61: 11620.7
... A114: 31867 | B114: 293128 | C114: 155439 | D114: 51615 | E114: 10873.2
A115: 31958 | B115: 297464 | C115: 158041 | D115: 54107 | E115: 10962.9 | G115: 163001
A116: 32050 | B116: 304555 | C116: 161305 | D116: 59096 | E116: 11079.9 | G116: 166402
A117: 32142 | B117: 308624 | C117: 164878 | D117: 60521 | E117: 11190.4 | G117: 170067
A118: 32233 | B118: 313316 | C118: 167118 | D118: 63524 | E118: 11302.2 | G118: 172527
A119: 32324 | B119: 313997 | C119: 169500 | D119: 65224 | E119: 11390.6 | G119: 174935
A120: 32416 | B120: 318223 | C120: 173440 | D120: 65803 | E120: 11480.3 | F120: 6.9176342 | G120: 178995
A121: 32508 | B121: 320612 | C121: 174977 | D121: 65739 | E121: 11572.6 | F121: 6.8467184 | G121: 180615
A122: 32598 | B122: 322258 | C122: 176456 | D122: 69251 | E122: 11685.7 | F122: 5.9973444 | G122: 182055
A123: 32689 | B123: 323569 | C123: 177960 | D123: 67897 | E123: 11753.3 | F123: 5.2760495 | G123: 183530
A124: 32781 | B124: 323542 | C124: 177788 | D124: 68657 | E124: 11785.8 | F124: 4.3000088 | G124: 183492
A125: 32873 | B125: 324139 | C125: 178541 | D125: 67315 | E125: 11814.4 | F125: 3.6664544 | G125: 184364
A126: 32963 | B126: 326896 | C126: 180618 | D126: 67750 | E126: 11805.3 | F126: 3.8208033 | G126: 186677
A127: 33054 | B127: 328047 | C127: 180979 | D127: 66791 | E127: 11785.8 | F127: 3.7435205 | G127: 186943
A128: 33146 | B128: 324080 | C128: 179811 | D128: 66185 | E128: 11723.4 | F128: 1.6861858 | G128: 185841
A129: 33238 | B129: 322743 | C129: 179595 | D129: 65453 | E129: 11601.2 | F129: 0.5688461 | G129: 185681
A130: 33328 | B130: 321164 | C130: 179314 | D130: 62473 | E130: 11458.2 | F130: -0.39349521 | G130: 185312
A131: 33419 | B131: 319958 | C131: 178053 | D131: 61542 | E131: 11307.4 | F131: -1.2267463 | G131: 184049
... A259: 45107 | B259: 559956 | C259: 340812 | D259: 106647 | E259: 13603.2 | F259: 0.48418767 | G259: 351570.61
A260: 45199 | F260: 0.3866 | G260: 352765.95
A261: 45291 | F261: 0.2938 | G261: 353453.21

Sheet QuarterlyData
A2: 1960
A3: 2021 | B3: 1
A4: dates | B4: GDP_Q | C4: CONS | D4: INV | E4: HOURS
A5: =IF(QuarterlyFAME!A5=0,"",QuarterlyFAME!A5) | B5: =IF(QuarterlyFAME!B5=0,"",QuarterlyFAME!B5) -> abmi.q | C5: =IF(QuarterlyFAME!C5=0,"",QuarterlyFAME!C5) -> ons.uk.hhd.abjr.q | D5: =IF(QuarterlyFAME!D5=0,"",QuarterlyFAME!D5) -> ons.uk.ado.npqt.q | E5: =IF([3]QuarterlyFAME!E5=0,"",[3]QuarterlyFAME!E5) -> #REF!
A6: =IF(QuarterlyFAME!A6=0,"",QuarterlyFAME!A6) -> 22006 | B6: =IF(QuarterlyFAME!B6=0,"",QuarterlyFAME!B6) -> 151420 | C6: =IF(QuarterlyFAME!C6=0,"",QuarterlyFAME!C6) -> 77407 | D6: =IF(QuarterlyFAME!D6=0,"",QuarterlyFAME!D6) -> 22788 | E6: =IF([3]QuarterlyFAME!E6=0,"",[3]QuarterlyFAME!E6)
A7: =IF(QuarterlyFAME!A7=0,"",QuarterlyFAME!A7) -> 22097 | B7: =IF(QuarterlyFAME!B7=0,"",QuarterlyFAME!B7) -> 150230 | C7: =IF(QuarterlyFAME!C7=0,"",QuarterlyFAME!C7) -> 77150 | D7: =IF(QuarterlyFAME!D7=0,"",QuarterlyFAME!D7) -> 23452 | E7: =IF([3]QuarterlyFAME!E7=0,"",[3]QuarterlyFAME!E7)
A8: =IF(QuarterlyFAME!A8=0,"",QuarterlyFAME!A8) -> 22189 | B8: =IF(QuarterlyFAME!B8=0,"",QuarterlyFAME!B8) -> 152485 | C8: =IF(QuarterlyFAME!C8=0,"",QuarterlyFAME!C8) -> 77664 | D8: =IF(QuarterlyFAME!D8=0,"",QuarterlyFAME!D8) -> 23888 | E8: =IF([3]QuarterlyFAME!E8=0,"",[3]QuarterlyFAME!E8)
A9: =IF(QuarterlyFAME!A9=0,"",QuarterlyFAME!A9) -> 22281 | B9: =IF(QuarterlyFAME!B9=0,"",QuarterlyFAME!B9) -> 153552 | C9: =IF(QuarterlyFAME!C9=0,"",QuarterlyFAME!C9) -> 77682 | D9: =IF(QuarterlyFAME!D9=0,"",QuarterlyFAME!D9) -> 24647 | E9: =IF([3]QuarterlyFAME!E9=0,"",[3]QuarterlyFAME!E9)
A10: =IF(QuarterlyFAME!A10=0,"",QuarterlyFAME!A10) -> 22371 | B10: =IF(QuarterlyFAME!B10=0,"",QuarterlyFAME!B10) -> 155990 | C10: =IF(QuarterlyFAME!C10=0,"",QuarterlyFAME!C10) -> 79058 | D10: =IF(QuarterlyFAME!D10=0,"",QuarterlyFAME!D10) -> 25266 | E10: =IF([3]QuarterlyFAME!E10=0,"",[3]QuarterlyFAME!E10)
A11: =IF(QuarterlyFAME!A11=0,"",QuarterlyFAME!A11) -> 22462 | B11: =IF(QuarterlyFAME!B11=0,"",QuarterlyFAME!B11) -> 156572 | C11: =IF(QuarterlyFAME!C11=0,"",QuarterlyFAME!C11) -> 79093 | D11: =IF(QuarterlyFAME!D11=0,"",QuarterlyFAME!D11) -> 25693 | E11: =IF([3]QuarterlyFAME!E11=0,"",[3]QuarterlyFAME!E11)
A12: =IF(QuarterlyFAME!A12=0,"",QuarterlyFAME!A12) -> 22554 | B12: =IF(QuarterlyFAME!B12=0,"",QuarterlyFAME!B12) -> 155818 | C12: =IF(QuarterlyFAME!C12=0,"",QuarterlyFAME!C12) -> 79472 | D12: =IF(QuarterlyFAME!D12=0,"",QuarterlyFAME!D12) -> 26062 | E12: =IF([3]QuarterlyFAME!E12=0,"",[3]QuarterlyFAME!E12)
A13: =IF(QuarterlyFAME!A13=0,"",QuarterlyFAME!A13) -> 22646 | B13: =IF(QuarterlyFAME!B13=0,"",QuarterlyFAME!B13) -> 155436 | C13: =IF(QuarterlyFAME!C13=0,"",QuarterlyFAME!C13) -> 79509 | D13: =IF(QuarterlyFAME!D13=0,"",QuarterlyFAME!D13) -> 25426 | E13: =IF([3]QuarterlyFAME!E13=0,"",[3]QuarterlyFAME!E13)
A14: =IF(QuarterlyFAME!A14=0,"",QuarterlyFAME!A14) -> 22736 | B14: =IF(QuarterlyFAME!B14=0,"",QuarterlyFAME!B14) -> 156202 | C14: =IF(QuarterlyFAME!C14=0,"",QuarterlyFAME!C14) -> 80153 | D14: =IF(QuarterlyFAME!D14=0,"",QuarterlyFAME!D14) -> 25626 | E14: =IF([3]QuarterlyFAME!E14=0,"",[3]QuarterlyFAME!E14)
A15: =IF(QuarterlyFAME!A15=0,"",QuarterlyFAME!A15) -> 22827 | B15: =IF(QuarterlyFAME!B15=0,"",QuarterlyFAME!B15) -> 157678 | C15: =IF(QuarterlyFAME!C15=0,"",QuarterlyFAME!C15) -> 81490 | D15: =IF(QuarterlyFAME!D15=0,"",QuarterlyFAME!D15) -> 26205 | E15: =IF([3]QuarterlyFAME!E15=0,"",[3]QuarterlyFAME!E15)
A16: =IF(QuarterlyFAME!A16=0,"",QuarterlyFAME!A16) -> 22919 | B16: =IF(QuarterlyFAME!B16=0,"",QuarterlyFAME!B16) -> 158572 | C16: =IF(QuarterlyFAME!C16=0,"",QuarterlyFAME!C16) -> 80962 | D16: =IF(QuarterlyFAME!D16=0,"",QuarterlyFAME!D16) -> 26085 | E16: =IF([3]QuarterlyFAME!E16=0,"",[3]QuarterlyFAME!E16)
... A253: =IF(QuarterlyFAME!A253=0,"",QuarterlyFAME!A253) -> 44561 | B253: =IF(QuarterlyFAME!B253=0,"",QuarterlyFAME!B253) -> 554821 | C253: =IF(QuarterlyFAME!C253=0,"",QuarterlyFAME!C253) -> 333650 | D253: =IF(QuarterlyFAME!D253=0,"",QuarterlyFAME!D253) -> 96819 | E253: =IF([3]QuarterlyFAME!E253=0,"",[3]QuarterlyFAME!E253)
A254: =IF(QuarterlyFAME!A254=0,"",QuarterlyFAME!A254) -> 44651 | B254: =IF(QuarterlyFAME!B254=0,"",QuarterlyFAME!B254) -> 557524 | C254: =IF(QuarterlyFAME!C254=0,"",QuarterlyFAME!C254) -> 337725 | D254: =IF(QuarterlyFAME!D254=0,"",QuarterlyFAME!D254) -> 105123
A255: =IF(QuarterlyFAME!A255=0,"",QuarterlyFAME!A255) -> 44742 | B255: =IF(QuarterlyFAME!B255=0,"",QuarterlyFAME!B255) -> 557810 | C255: =IF(QuarterlyFAME!C255=0,"",QuarterlyFAME!C255) -> 338452 | D255: =IF(QuarterlyFAME!D255=0,"",QuarterlyFAME!D255) -> 102732
A256: =IF(QuarterlyFAME!A256=0,"",QuarterlyFAME!A256) -> 44834 | B256: =IF(QuarterlyFAME!B256=0,"",QuarterlyFAME!B256) -> 557286 | C256: =IF(QuarterlyFAME!C256=0,"",QuarterlyFAME!C256) -> 337395 | D256: =IF(QuarterlyFAME!D256=0,"",QuarterlyFAME!D256) -> 103858
A257: =IF(QuarterlyFAME!A257=0,"",QuarterlyFAME!A257) -> 44926 | B257: =IF(QuarterlyFAME!B257=0,"",QuarterlyFAME!B257) -> 558005 | C257: =IF(QuarterlyFAME!C257=0,"",QuarterlyFAME!C257) -> 338155 | D257: =IF(QuarterlyFAME!D257=0,"",QuarterlyFAME!D257) -> 104129
A258: =IF(QuarterlyFAME!A258=0,"",QuarterlyFAME!A258) -> 45016 | B258: =IF(QuarterlyFAME!B258=0,"",QuarterlyFAME!B258) -> 558812 | C258: =IF(QuarterlyFAME!C258=0,"",QuarterlyFAME!C258) -> 338285 | D258: =IF(QuarterlyFAME!D258=0,"",QuarterlyFAME!D258) -> 106661
A259: =IF(QuarterlyFAME!A259=0,"",QuarterlyFAME!A259) -> 45107 | B259: =IF(QuarterlyFAME!B259=0,"",QuarterlyFAME!B259) -> 559956 | C259: =IF(QuarterlyFAME!C259=0,"",QuarterlyFAME!C259) -> 340812 | D259: =IF(QuarterlyFAME!D259=0,"",QuarterlyFAME!D259) -> 106647
A260: =IF(QuarterlyFAME!A260=0,"",QuarterlyFAME!A260) -> 45199 | B260: =IF(QuarterlyFAME!B260=0,"",QuarterlyFAME!B260) | C260: =IF(QuarterlyFAME!C260=0,"",QuarterlyFAME!C260) | D260: =IF(QuarterlyFAME!D260=0,"",QuarterlyFAME!D260)
